[{"matchId":"8C2gFdMb","scrapeId":493061},{"matchId":"IszXceiO","scrapeId":493062},{"matchId":"baz44u8t","scrapeId":493063},{"matchId":"tO3wlKNa","scrapeId":493064},{"matchId":"xULBZK86","scrapeId":493065},{"matchId":"YyPfw39s","scrapeId":493066},{"matchId":"EZWmsCAF","scrapeId":493067},{"matchId":"0GIFFiuC","scrapeId":493068},{"matchId":"KCBESCeM","scrapeId":493069},{"matchId":"QgSB8i4j","scrapeId":493070},{"matchId":"tSFKKcco","scrapeId":493071},{"matchId":"EZnlTcKi","scrapeId":493072},{"matchId":"zqlpUw5o","scrapeId":493073},{"matchId":"zDqu3xqT","scrapeId":493074},{"matchId":"QaHkhLUA","scrapeId":493075},{"matchId":"jsPxeNph","scrapeId":493076},{"matchId":"CUQmIBWs","scrapeId":493077},{"matchId":"tz2emiX7","scrapeId":493078},{"matchId":"IXl5xzJk","scrapeId":493079},{"matchId":"bkusnmjn","scrapeId":493080},{"matchId":"Y7okF6LO","scrapeId":493081},{"matchId":"80lwI8y6","scrapeId":493082},{"matchId":"QNJa4k76","scrapeId":493083},{"matchId":"jNOzE2v3","scrapeId":493084},{"matchId":"4hof1Pfc","scrapeId":493085},{"matchId":"Wz1Wrtx4","scrapeId":493086},{"matchId":"rXF4TPyI","scrapeId":493087},{"matchId":"zmlFI8Na","scrapeId":493088},{"matchId":"fTSu4986","scrapeId":493089},{"matchId":"jZ8MafHK","scrapeId":493090},{"matchId":"hUFFtFAr","scrapeId":493091},{"matchId":"MsXCqrRM","scrapeId":493092},{"matchId":"Whv0nps4","scrapeId":493093},{"matchId":"xdbKiK1n","scrapeId":493094},{"matchId":"U5FIPQbF","scrapeId":493095},{"matchId":"CE4SKwXO","scrapeId":493096},{"matchId":"xU1VrjJE","scrapeId":493097},{"matchId":"0rNATQcB","scrapeId":493098},{"matchId":"2wvjBBcq","scrapeId":493099},{"matchId":"2NkSeWcd","scrapeId":493100},{"matchId":"U9FS7xii","scrapeId":493101},{"matchId":"WKzFlFjT","scrapeId":493102},{"matchId":"Gdf2C5VT","scrapeId":493103},{"matchId":"zLuoto4j","scrapeId":493104},{"matchId":"IFq5qago","scrapeId":493105},{"matchId":"CE0MiNo5","scrapeId":493106},{"matchId":"xppnjAA0","scrapeId":493107},{"matchId":"Eou7aEmE","scrapeId":493108},{"matchId":"Ct1OzVAD","scrapeId":493109},{"matchId":"QPxsOiR7","scrapeId":493110},{"matchId":"j7pUQgsk","scrapeId":493111},{"matchId":"4x7mEGcq","scrapeId":493112},{"matchId":"M7lPN5c3","scrapeId":493113},{"matchId":"jVQCKIKF","scrapeId":493114},{"matchId":"bH3uKoU4","scrapeId":493115},{"matchId":"x2FWL7ah","scrapeId":493116},{"matchId":"xlzb78pa","scrapeId":493117},{"matchId":"pWWy2D8J","scrapeId":493118},{"matchId":"Eo1xsCWg","scrapeId":493119},{"matchId":"rREOh9V5","scrapeId":493120},{"matchId":"bat2kzPD","scrapeId":493121},{"matchId":"MFrVns3F","scrapeId":493122},{"matchId":"Cj4cqCSo","scrapeId":493123},{"matchId":"xStJkqJd","scrapeId":493124},{"matchId":"pAuwgc8i","scrapeId":493125},{"matchId":"W6ieUDVj","scrapeId":493126},{"matchId":"AwODHzno","scrapeId":493127},{"matchId":"0tWqGAZe","scrapeId":493128},{"matchId":"CKRPLNgI","scrapeId":493129},{"matchId":"AV3iPyqD","scrapeId":493130},{"matchId":"2iLACba7","scrapeId":493131},{"matchId":"tEhJMrNE","scrapeId":493132},{"matchId":"I1KDnBuo","scrapeId":493133},{"matchId":"OvqIcyln","scrapeId":493134},{"matchId":"jROvpIJn","scrapeId":493135},{"matchId":"IaobXvzs","scrapeId":493136},{"matchId":"IFkIbf7m","scrapeId":493137},{"matchId":"nLtbylyF","scrapeId":493138},{"matchId":"phKSL8yS","scrapeId":493139},{"matchId":"WETrgHgE","scrapeId":493140},{"matchId":"OKK5E5C4","scrapeId":493141},{"matchId":"lj4VChy0","scrapeId":493142},{"matchId":"4fMcuerP","scrapeId":493143},{"matchId":"xKfAlJQC","scrapeId":493144},{"matchId":"fXMIb3lK","scrapeId":493145},{"matchId":"xbJZyts7","scrapeId":493146},{"matchId":"fBornQ4E","scrapeId":493147},{"matchId":"YPWanZbc","scrapeId":493148},{"matchId":"QJ9YVDEG","scrapeId":493149},{"matchId":"W0QVBhNp","scrapeId":493150},{"matchId":"Uiv4GYET","scrapeId":493151},{"matchId":"YqTwObGu","scrapeId":493152},{"matchId":"j3faWvgg","scrapeId":493153},{"matchId":"46YTGag6","scrapeId":493154},{"matchId":"IkzMILOg","scrapeId":493155},{"matchId":"UVYpH8mk","scrapeId":493156},{"matchId":"xYg6OjeF","scrapeId":493157},{"matchId":"CGiuAitM","scrapeId":493158},{"matchId":"YPW5ehRS","scrapeId":493159},{"matchId":"ryvgbfsA","scrapeId":493160},{"matchId":"hnPAoHc4","scrapeId":493161},{"matchId":"Eq2qrriC","scrapeId":493162},{"matchId":"CfSFPyzA","scrapeId":493163},{"matchId":"hUDzp4Ma","scrapeId":493164},{"matchId":"zXR4Wph0","scrapeId":493165},{"matchId":"xxpIukVD","scrapeId":493166},{"matchId":"2wt14m64","scrapeId":493167},{"matchId":"IkUZXB8U","scrapeId":493168},{"matchId":"hUikME9I","scrapeId":493169},{"matchId":"SM6PRIus","scrapeId":493170},{"matchId":"zVbcOqZl","scrapeId":493171},{"matchId":"GAmMW7R8","scrapeId":493172},{"matchId":"OG0z94Z1","scrapeId":493173},{"matchId":"zerlc7zj","scrapeId":493174},{"matchId":"rc394krG","scrapeId":493175},{"matchId":"8KO6pUjp","scrapeId":493176},{"matchId":"dSPSiCbA","scrapeId":493177},{"matchId":"KMQh8CRg","scrapeId":493178},{"matchId":"AZLyxTbB","scrapeId":493179},{"matchId":"CdNpAYds","scrapeId":493180},{"matchId":"ELLv1eKQ","scrapeId":493181},{"matchId":"6eIW2HkE","scrapeId":493182},{"matchId":"YiDIQmpK","scrapeId":493183},{"matchId":"rahgkbLE","scrapeId":493184},{"matchId":"lt9jVxUr","scrapeId":493185},{"matchId":"drUBxLy9","scrapeId":493186},{"matchId":"pnROGwFk","scrapeId":493187},{"matchId":"88OMJ6VT","scrapeId":493188},{"matchId":"r1wcPA1h","scrapeId":493189},{"matchId":"hl23HRJC","scrapeId":493190},{"matchId":"lvINABna","scrapeId":493191},{"matchId":"W2ocfj2I","scrapeId":493192},{"matchId":"U1TkXLMF","scrapeId":493193},{"matchId":"hIXd48n2","scrapeId":493194},{"matchId":"YgrbGEuc","scrapeId":493195},{"matchId":"WQLS0ZuA","scrapeId":493196},{"matchId":"KUIuuhJj","scrapeId":493197},{"matchId":"Q7spjIRi","scrapeId":493198},{"matchId":"AaacSEZp","scrapeId":493199},{"matchId":"Gz9Q8Txe","scrapeId":493200},{"matchId":"bu2iWNzJ","scrapeId":493201},{"matchId":"IP6WznMm","scrapeId":493202},{"matchId":"AJq5KQy7","scrapeId":493203},{"matchId":"dfUaNSil","scrapeId":493204},{"matchId":"WUBvIXF8","scrapeId":493205},{"matchId":"lnprDNCq","scrapeId":493206},{"matchId":"pbFFnPAE","scrapeId":493207},{"matchId":"nJNCcrDd","scrapeId":493208},{"matchId":"8U3SIhq5","scrapeId":493209},{"matchId":"0lCd5ZE5","scrapeId":493210},{"matchId":"hO8l7epg","scrapeId":493211},{"matchId":"nonNjz0C","scrapeId":493212},{"matchId":"6NST8ePN","scrapeId":493213},{"matchId":"EXRqwHVC","scrapeId":493214},{"matchId":"jVzPsuHs","scrapeId":493215},{"matchId":"pvefSaHf","scrapeId":493216},{"matchId":"fkILnU29","scrapeId":493217},{"matchId":"h8MdmBF0","scrapeId":493218},{"matchId":"Uket2Y5U","scrapeId":493219},{"matchId":"nXUG9b7t","scrapeId":493220},{"matchId":"IHj3jy7I","scrapeId":493221},{"matchId":"2srAD78E","scrapeId":493222},{"matchId":"0IcBh6Wl","scrapeId":493223},{"matchId":"OWnXvm2k","scrapeId":493224},{"matchId":"UFrbokPL","scrapeId":493225},{"matchId":"ldNOWkAS","scrapeId":493226},{"matchId":"Y7NKEjlp","scrapeId":493227},{"matchId":"MTspLhBG","scrapeId":493228},{"matchId":"zDLrHOho","scrapeId":493229},{"matchId":"OhOxLXgJ","scrapeId":493230},{"matchId":"0EwDQyQs","scrapeId":493231},{"matchId":"UVnsWc2K","scrapeId":493232},{"matchId":"M7joCxBl","scrapeId":493233},{"matchId":"2cJnv0oe","scrapeId":493234},{"matchId":"WOh3K038","scrapeId":493235},{"matchId":"ruYP6sZ8","scrapeId":493236},{"matchId":"fJiVp0Ck","scrapeId":493237},{"matchId":"6ajfqmyo","scrapeId":493238},{"matchId":"zyr7fDqn","scrapeId":493239},{"matchId":"zZHTNqRE","scrapeId":493240},{"matchId":"dACdzAbU","scrapeId":493241},{"matchId":"GfHyuYqa","scrapeId":493242},{"matchId":"8brG2epe","scrapeId":493243},{"matchId":"bwaI6ei7","scrapeId":493244},{"matchId":"KCV9Awhr","scrapeId":493245},{"matchId":"Iq9vebhe","scrapeId":493246},{"matchId":"6oNm5rG2","scrapeId":493247},{"matchId":"vZogq1gq","scrapeId":493248},{"matchId":"2klMt8Xp","scrapeId":493249},{"matchId":"rRbNhEQu","scrapeId":493250},{"matchId":"CpF3xgta","scrapeId":493251},{"matchId":"4KkQOZBa","scrapeId":493252},{"matchId":"rBAawZQh","scrapeId":493253},{"matchId":"GtScPooD","scrapeId":493254},{"matchId":"hvywU9Ws","scrapeId":493255},{"matchId":"2BmzXxmM","scrapeId":493256},{"matchId":"lnYUZv33","scrapeId":493257},{"matchId":"lYhdLulA","scrapeId":493258},{"matchId":"0CC1abRj","scrapeId":493259},{"matchId":"YeqE8244","scrapeId":493260},{"matchId":"2H8qgN4H","scrapeId":493261},{"matchId":"YyHSd55h","scrapeId":493262},{"matchId":"lW1T0E6Q","scrapeId":493263},{"matchId":"KdcP1fiK","scrapeId":493264},{"matchId":"S2YolyNK","scrapeId":493265},{"matchId":"M3lLCBGO","scrapeId":493266},{"matchId":"vLh0HZ1g","scrapeId":493267},{"matchId":"bBphJeXt","scrapeId":493268},{"matchId":"hAHV1f26","scrapeId":493269},{"matchId":"2J7NF19i","scrapeId":493270},{"matchId":"8IwmAIfQ","scrapeId":493271},{"matchId":"dIvWUhWh","scrapeId":493272},{"matchId":"IX0yhJYs","scrapeId":493273},{"matchId":"8biCikN1","scrapeId":493274},{"matchId":"OYeWDuv4","scrapeId":493275},{"matchId":"lGsl12fb","scrapeId":493276},{"matchId":"UBERq1PN","scrapeId":493277},{"matchId":"44T1k5en","scrapeId":493278},{"matchId":"0IsxZqB5","scrapeId":493279},{"matchId":"UybIIOQO","scrapeId":493280},{"matchId":"Eu4kP8ss","scrapeId":493281},{"matchId":"23FjReDR","scrapeId":493282},{"matchId":"8MDzVwE2","scrapeId":493283},{"matchId":"0Gj9EITL","scrapeId":493284},{"matchId":"pl6AgHid","scrapeId":493285},{"matchId":"fcCQ31F3","scrapeId":493286},{"matchId":"hUkelMFG","scrapeId":493287},{"matchId":"zDGQxOUu","scrapeId":493288},{"matchId":"IwbO4pED","scrapeId":493289},{"matchId":"4hRKnChS","scrapeId":493290},{"matchId":"2RFSLrlC","scrapeId":493291},{"matchId":"YR7C15qL","scrapeId":493292},{"matchId":"Q1443RE8","scrapeId":493293},{"matchId":"6qEOEn35","scrapeId":493294},{"matchId":"SCyYTQNr","scrapeId":493295},{"matchId":"UJABeXHG","scrapeId":493296},{"matchId":"rkae3OJP","scrapeId":493297},{"matchId":"KQfDWoaL","scrapeId":493298},{"matchId":"pSMXPMkm","scrapeId":493299},{"matchId":"l6vG7uzJ","scrapeId":493300},{"matchId":"KQnaBNzf","scrapeId":493301},{"matchId":"ObgjDq6s","scrapeId":493302},{"matchId":"EP7KI5rK","scrapeId":493303},{"matchId":"YTUXf2jD","scrapeId":493304},{"matchId":"UyYGbpil","scrapeId":493305},{"matchId":"2eXrHX4g","scrapeId":493306},{"matchId":"lUOMBxTD","scrapeId":493307},{"matchId":"pb9JidKp","scrapeId":493308},{"matchId":"YwtJ1xZF","scrapeId":493309},{"matchId":"C85kJ2EI","scrapeId":493310},{"matchId":"MFhYaRF6","scrapeId":493311},{"matchId":"QwfZQgGR","scrapeId":493312},{"matchId":"U9323aI3","scrapeId":493313},{"matchId":"Ya3TRcAr","scrapeId":493314},{"matchId":"OzalF0zP","scrapeId":493315},{"matchId":"YXbLJUjD","scrapeId":493316},{"matchId":"ARX6Xsjg","scrapeId":493317},{"matchId":"4lXAW15a","scrapeId":493318},{"matchId":"ruWEVLK5","scrapeId":493319},{"matchId":"OjmCUuzC","scrapeId":493320},{"matchId":"d4oKSJ4O","scrapeId":493321},{"matchId":"WfiaUdD1","scrapeId":493322},{"matchId":"pbJBw1jF","scrapeId":493323},{"matchId":"rgqfPAV4","scrapeId":493324},{"matchId":"KGFfmHIm","scrapeId":493325},{"matchId":"fw2L3Vai","scrapeId":493326},{"matchId":"vaZvgnk9","scrapeId":493327},{"matchId":"vstOgy6g","scrapeId":493328},{"matchId":"Y1hBofj1","scrapeId":493329},{"matchId":"figOhIwT","scrapeId":493330},{"matchId":"v147RuuU","scrapeId":493331},{"matchId":"ATp72Y51","scrapeId":493332},{"matchId":"CzxZ3TmF","scrapeId":493333},{"matchId":"YL6U4ztR","scrapeId":493334},{"matchId":"tnIf5OCC","scrapeId":493335},{"matchId":"n90JLmiG","scrapeId":493336},{"matchId":"OOG6vK2n","scrapeId":493337},{"matchId":"2y5BtxGf","scrapeId":493338},{"matchId":"8YkFZT2A","scrapeId":493339},{"matchId":"6ZxkCZ4n","scrapeId":493340},{"matchId":"C0c0oOxC","scrapeId":493341},{"matchId":"h4f0f4gB","scrapeId":493342},{"matchId":"z3ncC0VO","scrapeId":493343},{"matchId":"fiPnS6q9","scrapeId":493344},{"matchId":"G0QrTnU2","scrapeId":493345},{"matchId":"EFrvtT8p","scrapeId":493346},{"matchId":"lIKvkPhB","scrapeId":493347},{"matchId":"MP1kZKe0","scrapeId":493348},{"matchId":"v96JKuIm","scrapeId":493349},{"matchId":"YLEQ94Sl","scrapeId":493350},{"matchId":"l4mQDSmS","scrapeId":493351},{"matchId":"h0GJuEyd","scrapeId":493352},{"matchId":"YTUGygyk","scrapeId":493353},{"matchId":"CpV89ibE","scrapeId":493354},{"matchId":"WGW6kW6r","scrapeId":493355},{"matchId":"zi8QPoSj","scrapeId":493356},{"matchId":"jgm3dp3S","scrapeId":493357},{"matchId":"b5yv8M0l","scrapeId":493358},{"matchId":"lYhGhs11","scrapeId":493359},{"matchId":"hllXhjep","scrapeId":493360},{"matchId":"IqZIrExC","scrapeId":493361},{"matchId":"h6s3kHlh","scrapeId":493362},{"matchId":"fkKf4LSm","scrapeId":493363},{"matchId":"Eg7HNB6t","scrapeId":493364},{"matchId":"4KDGJKBM","scrapeId":493365},{"matchId":"4r0UK9ja","scrapeId":493366},{"matchId":"QobyKUwT","scrapeId":493367},{"matchId":"ddLoAhxs","scrapeId":493368},{"matchId":"4p1Y2yVD","scrapeId":493369},{"matchId":"M3lRJtWF","scrapeId":493370},{"matchId":"f9zZszgl","scrapeId":493371},{"matchId":"rqOsPeWQ","scrapeId":493372},{"matchId":"hlMiVyho","scrapeId":493373},{"matchId":"0jLsNv0O","scrapeId":493374},{"matchId":"A1SUPtG5","scrapeId":493375},{"matchId":"WdlhCNo6","scrapeId":493376},{"matchId":"S4opIhIR","scrapeId":493377},{"matchId":"nDEBGXP5","scrapeId":493378},{"matchId":"pM5ocit2","scrapeId":493379},{"matchId":"YPYDChBg","scrapeId":493380},{"matchId":"8OWLiRkA","scrapeId":493381},{"matchId":"YVwkNtIf","scrapeId":493382},{"matchId":"Sf6Pjj5G","scrapeId":493383},{"matchId":"pOCcLJbc","scrapeId":493384},{"matchId":"KfUeGk1f","scrapeId":493385},{"matchId":"jJOKODgE","scrapeId":493386},{"matchId":"lj2k9YgR","scrapeId":493387},{"matchId":"tKwHBafI","scrapeId":493388},{"matchId":"M13ZsdeS","scrapeId":493389},{"matchId":"SUWcr5kB","scrapeId":493390},{"matchId":"6XR72TyJ","scrapeId":493391},{"matchId":"v7Hm7iNm","scrapeId":493392},{"matchId":"E3YPiCN0","scrapeId":493393},{"matchId":"MTL9gDyi","scrapeId":493394},{"matchId":"bN2Op27i","scrapeId":493395},{"matchId":"jBUHhaJg","scrapeId":493396},{"matchId":"MHReVo75","scrapeId":493397},{"matchId":"rk9zQjVP","scrapeId":493398},{"matchId":"0UZW5Vwf","scrapeId":493399},{"matchId":"tQ26kAgD","scrapeId":493400},{"matchId":"t4RVxX97","scrapeId":493401},{"matchId":"KICmwt4j","scrapeId":493402},{"matchId":"MqOAXGGU","scrapeId":493403},{"matchId":"rZCBOLXa","scrapeId":493404},{"matchId":"AN9qLnR7","scrapeId":493405},{"matchId":"xGMdUj4L","scrapeId":493406},{"matchId":"f5MESpDH","scrapeId":493407},{"matchId":"QeyNHDKF","scrapeId":493408},{"matchId":"GQHv5zyA","scrapeId":493409},{"matchId":"pS4MEBrT","scrapeId":493410},{"matchId":"drfsIPXN","scrapeId":493411},{"matchId":"jPyUMmJh","scrapeId":493412},{"matchId":"4E0a78J5","scrapeId":493413},{"matchId":"Ue8nAAZn","scrapeId":493414},{"matchId":"0IktgIbe","scrapeId":493415},{"matchId":"KOedetwq","scrapeId":493416},{"matchId":"E3hxw68c","scrapeId":493417},{"matchId":"hzPfQSOi","scrapeId":493418},{"matchId":"hxGWLDX5","scrapeId":493419},{"matchId":"dQElP8sU","scrapeId":493420},{"matchId":"SYW86YXI","scrapeId":493421},{"matchId":"tIUd9zl0","scrapeId":493422},{"matchId":"KQMW4LdE","scrapeId":493423},{"matchId":"txX1EKUf","scrapeId":493424},{"matchId":"nFBSaLF1","scrapeId":493425},{"matchId":"QsCq0U9p","scrapeId":493426},{"matchId":"AeVwgD2H","scrapeId":493427},{"matchId":"GY94vEmO","scrapeId":493428},{"matchId":"E7rjwA62","scrapeId":493429},{"matchId":"YZ7HOAi9","scrapeId":493430},{"matchId":"bHgZBX73","scrapeId":493431},{"matchId":"OC8NoZol","scrapeId":493432},{"matchId":"l2ShH7So","scrapeId":493433},{"matchId":"EXBIFfis","scrapeId":493434},{"matchId":"lhsC2z2n","scrapeId":493435},{"matchId":"QBe17PmE","scrapeId":493436},{"matchId":"vohvhplR","scrapeId":493437},{"matchId":"6e0Rfn48","scrapeId":493438},{"matchId":"IBulsTZ8","scrapeId":493439},{"matchId":"A5IMQ7kS","scrapeId":493440},{"matchId":"joa7QfMN","scrapeId":493441},{"matchId":"GWlN10Ga","scrapeId":493442},{"matchId":"2Nyyj3Hm","scrapeId":493443},{"matchId":"27mDzOH0","scrapeId":493444},{"matchId":"Gjo1wQXs","scrapeId":493445},{"matchId":"WpUPubxq","scrapeId":493446},{"matchId":"bZQcxPVj","scrapeId":493447},{"matchId":"QXdp1ePq","scrapeId":493448},{"matchId":"jBEFXUSA","scrapeId":493449},{"matchId":"UsoYKiq5","scrapeId":493450},{"matchId":"dzE74WbO","scrapeId":493451},{"matchId":"AJkQigFI","scrapeId":493452},{"matchId":"zswlh291","scrapeId":493453},{"matchId":"URv60Q1L","scrapeId":493454},{"matchId":"Q9MsG8dp","scrapeId":493455},{"matchId":"tMr9JKrp","scrapeId":493456},{"matchId":"YeTJ5n8f","scrapeId":493457},{"matchId":"8K2rKHcI","scrapeId":493458},{"matchId":"WE7JPLTt","scrapeId":493459},{"matchId":"hKADGriQ","scrapeId":493460},{"matchId":"2a9jKTZg","scrapeId":493461},{"matchId":"IPpZJdtL","scrapeId":493462},{"matchId":"lhmsae4e","scrapeId":493463},{"matchId":"UgcTlX9T","scrapeId":493464},{"matchId":"naBsESyk","scrapeId":493465},{"matchId":"tEb0eHQo","scrapeId":493466},{"matchId":"0xhQg4ks","scrapeId":493467},{"matchId":"MVrTPPz1","scrapeId":493468},{"matchId":"hxj8aTMe","scrapeId":493469},{"matchId":"AekTbdWp","scrapeId":493470},{"matchId":"MFCRjavO","scrapeId":493471},{"matchId":"KjGAfsua","scrapeId":493472},{"matchId":"W6eXtOAa","scrapeId":493473},{"matchId":"COXsGCWj","scrapeId":493474},{"matchId":"EkXPt3g2","scrapeId":493475},{"matchId":"z1wUOUXG","scrapeId":493476},{"matchId":"GYZXh9nc","scrapeId":493477},{"matchId":"K6KgujIc","scrapeId":493478},{"matchId":"xnpj3ymG","scrapeId":493479},{"matchId":"CtSuqGep","scrapeId":493480},{"matchId":"d42cgKYc","scrapeId":493481},{"matchId":"ANSEvLJ4","scrapeId":493482},{"matchId":"Cp8CSNKh","scrapeId":493483},{"matchId":"tEgrv027","scrapeId":493484},{"matchId":"YJrpRMI1","scrapeId":493485},{"matchId":"KbR826kj","scrapeId":493486},{"matchId":"SGUCBAS3","scrapeId":493487},{"matchId":"jm3x8yMB","scrapeId":493488},{"matchId":"MkzihdMO","scrapeId":493489},{"matchId":"byoKBJID","scrapeId":493490},{"matchId":"6T8isu86","scrapeId":493491},{"matchId":"8SwEj30Q","scrapeId":493492},{"matchId":"OhNFwQGK","scrapeId":493493},{"matchId":"n5qsmLn3","scrapeId":493494},{"matchId":"fRvvRwQq","scrapeId":493495},{"matchId":"O0RWSQeU","scrapeId":493496},{"matchId":"t8QXFmCO","scrapeId":493497},{"matchId":"CGMb7OHD","scrapeId":493498},{"matchId":"IBW38KTk","scrapeId":493499},{"matchId":"r3DdMXSt","scrapeId":493500},{"matchId":"QaKnAQXf","scrapeId":493501},{"matchId":"r9za7XBd","scrapeId":493502},{"matchId":"jRw3GykA","scrapeId":493503},{"matchId":"vR6NH6A8","scrapeId":493504},{"matchId":"IDcGd5Yr","scrapeId":493505},{"matchId":"pI012fKA","scrapeId":493506},{"matchId":"hGHFlyjB","scrapeId":493507},{"matchId":"xz8XXF5U","scrapeId":493508},{"matchId":"xWRYMbiC","scrapeId":493509},{"matchId":"lxKr8axJ","scrapeId":493510},{"matchId":"ruHzAL76","scrapeId":493511},{"matchId":"2D5hAlHe","scrapeId":493512},{"matchId":"KQhKFLGJ","scrapeId":493513},{"matchId":"htnZftAs","scrapeId":493514},{"matchId":"h2u9xafD","scrapeId":493515},{"matchId":"dEfNpP2E","scrapeId":493516},{"matchId":"8ncnPRnI","scrapeId":493517},{"matchId":"bPhVFbrU","scrapeId":493518},{"matchId":"f9G9sCR9","scrapeId":493519},{"matchId":"6JzEPjsT","scrapeId":493520},{"matchId":"4z8oYrfo","scrapeId":493521},{"matchId":"hSxnt7n5","scrapeId":493522},{"matchId":"xW1HxO10","scrapeId":493523},{"matchId":"fm3g6yS7","scrapeId":493524},{"matchId":"0zkqEu5L","scrapeId":493525},{"matchId":"U1kKjbr2","scrapeId":493526},{"matchId":"hSff0Oj3","scrapeId":493527},{"matchId":"ALUodPyA","scrapeId":493528},{"matchId":"KAQrzrFj","scrapeId":493529},{"matchId":"xzPRsnh4","scrapeId":493530},{"matchId":"WlzsxX0I","scrapeId":493531},{"matchId":"M7ULpHOP","scrapeId":493532},{"matchId":"GA7tGvQQ","scrapeId":493533},{"matchId":"WYsq7TPt","scrapeId":493534},{"matchId":"p4GxUDKQ","scrapeId":493535},{"matchId":"KSaiaDZd","scrapeId":493536},{"matchId":"4vctfSca","scrapeId":493537},{"matchId":"pnxchFMf","scrapeId":493538},{"matchId":"jq7HacUK","scrapeId":493539},{"matchId":"f30JPdw2","scrapeId":493540},{"matchId":"nVpLZt19","scrapeId":493541},{"matchId":"80esK11M","scrapeId":493542},{"matchId":"dCtEOPni","scrapeId":493543},{"matchId":"rkI6KUAB","scrapeId":493544},{"matchId":"Eo287iR5","scrapeId":493545},{"matchId":"tlnqBZRt","scrapeId":493546},{"matchId":"Gb8G9PV6","scrapeId":493547},{"matchId":"ngDGJ9gE","scrapeId":493548},{"matchId":"K23DcSWf","scrapeId":493549},{"matchId":"bN7j5wlA","scrapeId":493550},{"matchId":"0rO8jvZG","scrapeId":493551},{"matchId":"M77mgtkb","scrapeId":493552},{"matchId":"YPFBoTon","scrapeId":493553},{"matchId":"KdtfuNKb","scrapeId":493554},{"matchId":"pvlsrPzt","scrapeId":493555},{"matchId":"2RSSYobP","scrapeId":493556},{"matchId":"pUMXAr6I","scrapeId":493557},{"matchId":"OUdnCi01","scrapeId":493558},{"matchId":"SUFC5GwS","scrapeId":493559},{"matchId":"IgZjAvPd","scrapeId":493560},{"matchId":"A571euA3","scrapeId":493561},{"matchId":"4630Gnxs","scrapeId":493562},{"matchId":"pGPUfBbN","scrapeId":493563},{"matchId":"KWUhiY3f","scrapeId":493564},{"matchId":"QwiYgv8C","scrapeId":493565},{"matchId":"Uo8MbM8m","scrapeId":493566},{"matchId":"6PCmr1O6","scrapeId":493567},{"matchId":"4dv0i51K","scrapeId":493568},{"matchId":"0rWhW3Pf","scrapeId":493569},{"matchId":"Io7MBM4F","scrapeId":493570},{"matchId":"2VKFOnIR","scrapeId":493571},{"matchId":"nDJGOeCA","scrapeId":493572},{"matchId":"WU4AEOKd","scrapeId":493573},{"matchId":"joQ7QHsb","scrapeId":493574},{"matchId":"EgSxDIS4","scrapeId":493575},{"matchId":"h0X3dcrO","scrapeId":493576},{"matchId":"nuxWuGmo","scrapeId":493577},{"matchId":"2RMZ0LTh","scrapeId":493578},{"matchId":"8QG5qKbI","scrapeId":493579},{"matchId":"pbM1fp7J","scrapeId":493580},{"matchId":"I7CbY2p0","scrapeId":493581},{"matchId":"YyABGI10","scrapeId":493582},{"matchId":"291ON09Q","scrapeId":493583},{"matchId":"hQzsBsuR","scrapeId":493584},{"matchId":"nPPNhrJr","scrapeId":493585},{"matchId":"COAqb4eL","scrapeId":493586},{"matchId":"Or0JUELH","scrapeId":493587},{"matchId":"8dRBEmxU","scrapeId":493588},{"matchId":"Uaa9q5tS","scrapeId":493589},{"matchId":"6iusR5Kq","scrapeId":493590},{"matchId":"l0I3zw7n","scrapeId":493591},{"matchId":"0jdNyVQg","scrapeId":493592},{"matchId":"f5BqMkR6","scrapeId":493593},{"matchId":"nHqf7jCD","scrapeId":493594},{"matchId":"M9nrAhSf","scrapeId":493595},{"matchId":"Y1DlV2b3","scrapeId":493596},{"matchId":"YslO45VA","scrapeId":493597},{"matchId":"W0Mi6ckI","scrapeId":493598},{"matchId":"fasEMbSF","scrapeId":493599},{"matchId":"roD21rwo","scrapeId":493600},{"matchId":"ETaFIU3t","scrapeId":493601},{"matchId":"hddFxDCU","scrapeId":493602},{"matchId":"tKX8Vwam","scrapeId":493603},{"matchId":"nslzxsy1","scrapeId":493604},{"matchId":"bkVpBCYF","scrapeId":493605},{"matchId":"2NyxDY33","scrapeId":493606},{"matchId":"dQljkVBd","scrapeId":493607},{"matchId":"nZyblz9C","scrapeId":493608},{"matchId":"jaWXCjTA","scrapeId":493609},{"matchId":"jaA2cBTN","scrapeId":493610},{"matchId":"j5Zs4ept","scrapeId":493611},{"matchId":"fwK3jxGt","scrapeId":493612},{"matchId":"rajoYf0C","scrapeId":493613},{"matchId":"UTycfoHE","scrapeId":493614},{"matchId":"jPcKtSnF","scrapeId":493615},{"matchId":"23HPKpQe","scrapeId":493616},{"matchId":"rwJyWAYd","scrapeId":493617},{"matchId":"p6Tu41qm","scrapeId":493618},{"matchId":"UZh2HBJ3","scrapeId":493619},{"matchId":"AVPu0AlT","scrapeId":493620},{"matchId":"KpmUsBSp","scrapeId":493621},{"matchId":"pph5iOas","scrapeId":493622},{"matchId":"YiJojE37","scrapeId":493623},{"matchId":"GxhxaoVC","scrapeId":493624},{"matchId":"p8b8xeZ7","scrapeId":493625},{"matchId":"CfO8l1S2","scrapeId":493626},{"matchId":"OYsESJ5q","scrapeId":493627},{"matchId":"2i3kQQqo","scrapeId":493628},{"matchId":"4G1qHm7U","scrapeId":493629},{"matchId":"v94XJkNB","scrapeId":493630},{"matchId":"vePb5j8I","scrapeId":493631},{"matchId":"d8i7FzWP","scrapeId":493632},{"matchId":"OldtPef1","scrapeId":493633},{"matchId":"MVvVFqQ8","scrapeId":493634},{"matchId":"AVmfk8h1","scrapeId":493635},{"matchId":"z11l36t3","scrapeId":493636},{"matchId":"IaVgwIIl","scrapeId":493637},{"matchId":"Yk8sGjQM","scrapeId":493638},{"matchId":"4tFF74GF","scrapeId":493639},{"matchId":"f9WihPGS","scrapeId":493640},{"matchId":"CCLXdm2c","scrapeId":493641},{"matchId":"va1fqUXc","scrapeId":493642},{"matchId":"rXoGVA3b","scrapeId":493643},{"matchId":"t6jfsmoD","scrapeId":493644},{"matchId":"2uNooVol","scrapeId":493645},{"matchId":"fFc8XBHl","scrapeId":493646},{"matchId":"0hxZIC2e","scrapeId":493647},{"matchId":"8fcfQfAL","scrapeId":493648},{"matchId":"nRTCDHQF","scrapeId":493649},{"matchId":"fD6uDpz5","scrapeId":493650},{"matchId":"8bm6sgpK","scrapeId":493651},{"matchId":"CUlk2TLn","scrapeId":493652},{"matchId":"AmDKnlMa","scrapeId":493653},{"matchId":"tSZyeCEJ","scrapeId":493654},{"matchId":"fwYRtMg9","scrapeId":493655},{"matchId":"GG8CWbKS","scrapeId":493656},{"matchId":"ltcSLKHq","scrapeId":493657},{"matchId":"dK3PSYDT","scrapeId":493658},{"matchId":"OUBCVzUA","scrapeId":493659},{"matchId":"bD9oHyFH","scrapeId":493660},{"matchId":"UXHUKJFh","scrapeId":493661},{"matchId":"84lm8tWn","scrapeId":493662},{"matchId":"YqFqB9nR","scrapeId":493663},{"matchId":"Gzuu8KSR","scrapeId":493664},{"matchId":"fVPuLUmH","scrapeId":493665},{"matchId":"zmGHUsLD","scrapeId":493666},{"matchId":"lS3PuQD8","scrapeId":493667},{"matchId":"ruKrlq8H","scrapeId":493668},{"matchId":"fkYJ7u2P","scrapeId":493669},{"matchId":"0ADtysRm","scrapeId":493670},{"matchId":"Y7aSIJn0","scrapeId":493671},{"matchId":"hWUaO3sr","scrapeId":493672},{"matchId":"l20fR8i9","scrapeId":493673},{"matchId":"0xYpznRI","scrapeId":493674},{"matchId":"OdWYbQh8","scrapeId":493675},{"matchId":"2iovwqWl","scrapeId":493676},{"matchId":"ERCjnm92","scrapeId":493677},{"matchId":"GdCHZ9Pd","scrapeId":493678},{"matchId":"6oqaHS9S","scrapeId":493679},{"matchId":"tvbZMWui","scrapeId":493680},{"matchId":"zsBmaTmp","scrapeId":493681},{"matchId":"UJSJTas0","scrapeId":493682},{"matchId":"vZLnyrkQ","scrapeId":493683},{"matchId":"rmxpHMcf","scrapeId":493684},{"matchId":"8UN14qEl","scrapeId":493685},{"matchId":"jVYNBRLE","scrapeId":493686},{"matchId":"fqkLi6Ur","scrapeId":493687},{"matchId":"xS8lcS6L","scrapeId":493688},{"matchId":"zs1nG54L","scrapeId":493689},{"matchId":"2iaJf6kD","scrapeId":493690},{"matchId":"fRFPnbkJ","scrapeId":493691},{"matchId":"hxOz8N4C","scrapeId":493692},{"matchId":"WfwuSf8t","scrapeId":493693},{"matchId":"OdWJB55m","scrapeId":493694},{"matchId":"UeEoUDLE","scrapeId":493695},{"matchId":"x2Ra6AT7","scrapeId":493696},{"matchId":"pjNqXHB4","scrapeId":493697},{"matchId":"MahhdcTQ","scrapeId":493698},{"matchId":"pzRW00cb","scrapeId":493699},{"matchId":"tznK5xjD","scrapeId":493700},{"matchId":"2gIn3g52","scrapeId":493701},{"matchId":"nTKR7E9k","scrapeId":493702},{"matchId":"bTJrmvYM","scrapeId":493703},{"matchId":"4MWEwe9f","scrapeId":493704},{"matchId":"GjqpqSOn","scrapeId":493705},{"matchId":"xhUhzxbb","scrapeId":493706},{"matchId":"UiIYkvbt","scrapeId":493707},{"matchId":"Ct7oFAuT","scrapeId":493708},{"matchId":"dxwHHJTe","scrapeId":493709},{"matchId":"zmMS8koO","scrapeId":493710},{"matchId":"S0LErgXI","scrapeId":493711},{"matchId":"OKdcf1h5","scrapeId":493712},{"matchId":"QB17d0v4","scrapeId":493713},{"matchId":"6ajYm0k3","scrapeId":493714},{"matchId":"4O9rXqBh","scrapeId":493715},{"matchId":"UXHXIgjr","scrapeId":493716},{"matchId":"zHNqav2m","scrapeId":493717},{"matchId":"IkjJ1dah","scrapeId":493718},{"matchId":"p6BSrTBe","scrapeId":493719},{"matchId":"zLebtTId","scrapeId":493720},{"matchId":"SdoN2SWd","scrapeId":493721},{"matchId":"0WUgSoep","scrapeId":493722},{"matchId":"2yaFOcGs","scrapeId":493723},{"matchId":"nTM1ZaC9","scrapeId":493724},{"matchId":"pKtPCRqM","scrapeId":493725},{"matchId":"2yPY1AV3","scrapeId":493726},{"matchId":"r5kvioOb","scrapeId":493727},{"matchId":"nBRvSNPD","scrapeId":493728},{"matchId":"SlLDIy56","scrapeId":493729},{"matchId":"A3FPMS1K","scrapeId":493730},{"matchId":"x8pjgXUM","scrapeId":493731},{"matchId":"lSo5fFNn","scrapeId":493732},{"matchId":"ttPow7Fk","scrapeId":493733},{"matchId":"roPosGGN","scrapeId":493734},{"matchId":"xlr9bHob","scrapeId":493735},{"matchId":"rXqDSG1U","scrapeId":493736},{"matchId":"4to9TdnO","scrapeId":493737},{"matchId":"lpepZ0In","scrapeId":493738},{"matchId":"McXMHamC","scrapeId":493739},{"matchId":"zsVAK13g","scrapeId":493740},{"matchId":"APSq62l0","scrapeId":493741},{"matchId":"MZlzR3QP","scrapeId":493742},{"matchId":"0nNbRCK8","scrapeId":493743},{"matchId":"nqcPCD5F","scrapeId":493744},{"matchId":"8hbLDgj9","scrapeId":493745},{"matchId":"8UqcDPvT","scrapeId":493746},{"matchId":"C2jlFoAG","scrapeId":493747},{"matchId":"WYineQIp","scrapeId":493748},{"matchId":"CIEdiW19","scrapeId":493749},{"matchId":"6mCwPFm2","scrapeId":493750},{"matchId":"O8jXjVyJ","scrapeId":493751},{"matchId":"l8ijjbo8","scrapeId":493752},{"matchId":"jFrJEYTP","scrapeId":493753},{"matchId":"CA4t1FaQ","scrapeId":493754},{"matchId":"llc4EJRb","scrapeId":493755},{"matchId":"CpV5Txnq","scrapeId":493756},{"matchId":"EifJm5P9","scrapeId":493757},{"matchId":"xzklD3Wa","scrapeId":493758},{"matchId":"IXYnFP1m","scrapeId":493759},{"matchId":"pMRGCWuk","scrapeId":493760},{"matchId":"j7byPeIP","scrapeId":493761},{"matchId":"EJC35FYL","scrapeId":493762},{"matchId":"nquCPCpD","scrapeId":493763},{"matchId":"QHAIpi0i","scrapeId":493764},{"matchId":"Ews0S9pN","scrapeId":493765},{"matchId":"EP1RDAVT","scrapeId":493766},{"matchId":"Qsf9JE1h","scrapeId":493767},{"matchId":"pQDgPqYD","scrapeId":493768},{"matchId":"IJL71tt7","scrapeId":493769},{"matchId":"AVwHBQ3E","scrapeId":493770},{"matchId":"M9LUaT42","scrapeId":493771},{"matchId":"hYVFrSZR","scrapeId":493772},{"matchId":"C05uo0vT","scrapeId":493773},{"matchId":"tdXTS0Ip","scrapeId":493774},{"matchId":"hYFinkJ5","scrapeId":493775},{"matchId":"negQVTYO","scrapeId":493776},{"matchId":"tKuwsfsQ","scrapeId":493777},{"matchId":"6scWNEzl","scrapeId":493778},{"matchId":"6sy18Zz1","scrapeId":493779},{"matchId":"vR7DHwEE","scrapeId":493780},{"matchId":"dWmVHn8c","scrapeId":493781},{"matchId":"phKCa5hT","scrapeId":493782},{"matchId":"IJDj6k9o","scrapeId":493783},{"matchId":"WSI2YSgU","scrapeId":493784},{"matchId":"ULDvvXPh","scrapeId":493785},{"matchId":"GIm5PXAa","scrapeId":493786},{"matchId":"zurvvC8e","scrapeId":493787},{"matchId":"vDlVuYwq","scrapeId":493788},{"matchId":"n1UHYGWF","scrapeId":493789},{"matchId":"KhVvZT7t","scrapeId":493790},{"matchId":"8E1MGnhC","scrapeId":493791},{"matchId":"StRm2mwJ","scrapeId":493792},{"matchId":"8WfhDDoK","scrapeId":493793},{"matchId":"buthl6Ci","scrapeId":493794},{"matchId":"8rZmAoaS","scrapeId":493795},{"matchId":"IiRgyaH5","scrapeId":493796},{"matchId":"juzwusIt","scrapeId":493797},{"matchId":"dIE3Qs3m","scrapeId":493798},{"matchId":"trISOURr","scrapeId":493799},{"matchId":"88nlspSA","scrapeId":493800},{"matchId":"hUyBkeyN","scrapeId":493801},{"matchId":"4zKAK2Nj","scrapeId":493802},{"matchId":"t2IxQbv5","scrapeId":493803},{"matchId":"CMQLTtut","scrapeId":493804},{"matchId":"xAajE1ug","scrapeId":493805},{"matchId":"COeS9nl7","scrapeId":493806},{"matchId":"na3tJjRK","scrapeId":493807},{"matchId":"xUqb6DsF","scrapeId":493808},{"matchId":"4Goj8ZC2","scrapeId":493809},{"matchId":"ro9JfGr3","scrapeId":493810},{"matchId":"Wd2YWCjd","scrapeId":493811},{"matchId":"2HlnLFip","scrapeId":493812},{"matchId":"EgX9v4h5","scrapeId":493813},{"matchId":"lnAOS6gg","scrapeId":493814},{"matchId":"z3CzQ4wC","scrapeId":493815},{"matchId":"8INBRdcJ","scrapeId":493816},{"matchId":"8beQFab7","scrapeId":493817},{"matchId":"trSxP3yL","scrapeId":493818},{"matchId":"0ETz5rpk","scrapeId":493819},{"matchId":"tQG2Nj0G","scrapeId":493820},{"matchId":"fgQSADGA","scrapeId":493821},{"matchId":"YwxKCZob","scrapeId":493822},{"matchId":"KzCpbzX4","scrapeId":493823},{"matchId":"ELTOtZ1U","scrapeId":493824},{"matchId":"ULqWR7Y7","scrapeId":493825},{"matchId":"6cXuW7HP","scrapeId":493826},{"matchId":"250qRcE0","scrapeId":493827},{"matchId":"tI8K1sok","scrapeId":493828},{"matchId":"2kfH6WWG","scrapeId":493829},{"matchId":"4GmAUxKa","scrapeId":493830},{"matchId":"0O6Xkmj8","scrapeId":493831},{"matchId":"l0an4GqQ","scrapeId":493832},{"matchId":"x8E8QWMd","scrapeId":493833},{"matchId":"nJPp51Zj","scrapeId":493834},{"matchId":"YoW6xDOt","scrapeId":493835},{"matchId":"MDwNqAZA","scrapeId":493836},{"matchId":"hYaNjhp6","scrapeId":493837},{"matchId":"rwanaGxQ","scrapeId":493838},{"matchId":"hhMzsHGs","scrapeId":493839},{"matchId":"tEhIOZ0D","scrapeId":493840},{"matchId":"Eq6RYJOK","scrapeId":493841},{"matchId":"W0QSDIne","scrapeId":493842},{"matchId":"Ic0gaJX1","scrapeId":493843},{"matchId":"hjV7MkZc","scrapeId":493844},{"matchId":"rLmHaSRp","scrapeId":493845},{"matchId":"OdbIBYKu","scrapeId":493846},{"matchId":"CIY3hBKH","scrapeId":493847},{"matchId":"AkrLX8U0","scrapeId":493848},{"matchId":"IeNSfqPI","scrapeId":493849},{"matchId":"KtR7a7Am","scrapeId":493850},{"matchId":"2kSlqnQ6","scrapeId":493851},{"matchId":"Y9zYnUQs","scrapeId":493852},{"matchId":"rsmVkcsM","scrapeId":493853},{"matchId":"I7V3PEyU","scrapeId":493854},{"matchId":"E1aIhac3","scrapeId":493855},{"matchId":"6NGytMDc","scrapeId":493856},{"matchId":"djYDQtEA","scrapeId":493857},{"matchId":"CflouHZd","scrapeId":493858},{"matchId":"61u1TrUi","scrapeId":493859},{"matchId":"CM8iDWwf","scrapeId":493860},{"matchId":"bJrIbXO0","scrapeId":493861},{"matchId":"4KHVJS5i","scrapeId":493862},{"matchId":"Gt6GIWyG","scrapeId":493863},{"matchId":"YHGBJCM9","scrapeId":493864},{"matchId":"OrgSSYqH","scrapeId":493865},{"matchId":"rBIgEZUN","scrapeId":493866},{"matchId":"bNGsHyo5","scrapeId":493867},{"matchId":"b1u74b1a","scrapeId":493868},{"matchId":"WnPQOSnE","scrapeId":493869},{"matchId":"MHsz25u1","scrapeId":493870},{"matchId":"zm4gkSee","scrapeId":493871},{"matchId":"EXFpilRr","scrapeId":493872},{"matchId":"UoaurBlS","scrapeId":493873},{"matchId":"8WAWqXJF","scrapeId":493874},{"matchId":"zk5cXgzA","scrapeId":493875},{"matchId":"2aDpzdji","scrapeId":493876},{"matchId":"vaH5ZOat","scrapeId":493877},{"matchId":"MsmiG1aI","scrapeId":493878},{"matchId":"budWKPpm","scrapeId":493879},{"matchId":"KzIg76Gm","scrapeId":493880},{"matchId":"rgFQD8wK","scrapeId":493881},{"matchId":"Wf9pHMSE","scrapeId":493882},{"matchId":"v1MbgJz8","scrapeId":493883},{"matchId":"SpHFgSUj","scrapeId":493884},{"matchId":"vB9awcqk","scrapeId":493885},{"matchId":"AVJmiYVR","scrapeId":493886},{"matchId":"hzZlWWg2","scrapeId":493887},{"matchId":"KMbkrwmc","scrapeId":493888},{"matchId":"UizXPeXS","scrapeId":493889},{"matchId":"js1P6GQj","scrapeId":493890},{"matchId":"0b3sFvJA","scrapeId":493891},{"matchId":"4Ck9E7Sa","scrapeId":493892},{"matchId":"IemcH9rs","scrapeId":493893},{"matchId":"plf1o9bD","scrapeId":493894},{"matchId":"MTXI3jEs","scrapeId":493895},{"matchId":"pURFZBa1","scrapeId":493896},{"matchId":"YTWZrGxF","scrapeId":493897},{"matchId":"baGas31A","scrapeId":493898},{"matchId":"GGz1M1Pp","scrapeId":493899},{"matchId":"l07DV52b","scrapeId":493900},{"matchId":"MkmgUe6O","scrapeId":493901},{"matchId":"KQh3NfvH","scrapeId":493902},{"matchId":"EPNFGxxP","scrapeId":493903},{"matchId":"zZOBHIMI","scrapeId":493904},{"matchId":"MeUX5LN6","scrapeId":493905},{"matchId":"QTzP7sgf","scrapeId":493906},{"matchId":"KzGohLIP","scrapeId":493907},{"matchId":"vB9Sx7Ud","scrapeId":493908},{"matchId":"nHMtF3xj","scrapeId":493909},{"matchId":"OKd31p8j","scrapeId":493910},{"matchId":"OdEGAlo4","scrapeId":493911},{"matchId":"IwzYaXWo","scrapeId":493912},{"matchId":"f3wGATT6","scrapeId":493913},{"matchId":"YZ9Ycjp1","scrapeId":493914},{"matchId":"fLWo7fNE","scrapeId":493915},{"matchId":"0MkepXF1","scrapeId":493916},{"matchId":"6aEaecO2","scrapeId":493917},{"matchId":"jD9ovdgS","scrapeId":493918},{"matchId":"GfHYtb99","scrapeId":493919},{"matchId":"KACks73h","scrapeId":493920},{"matchId":"nHbSP5YH","scrapeId":493921},{"matchId":"AcOUGAkm","scrapeId":493922},{"matchId":"SxL5MWRP","scrapeId":493923},{"matchId":"tMdO9grK","scrapeId":493924},{"matchId":"dYMKkYjl","scrapeId":493925},{"matchId":"4IduA2x3","scrapeId":493926},{"matchId":"jFW5e3N9","scrapeId":493927},{"matchId":"Gf67FYT0","scrapeId":493928},{"matchId":"C6leOUoQ","scrapeId":493929},{"matchId":"IZok5kul","scrapeId":493930},{"matchId":"pIkuchmR","scrapeId":493931},{"matchId":"fXCTvgRr","scrapeId":493932},{"matchId":"bifQqrDA","scrapeId":493933},{"matchId":"821DnpTi","scrapeId":493934},{"matchId":"WGzqX4T4","scrapeId":493935},{"matchId":"W2eAI5EB","scrapeId":493936},{"matchId":"jqzy46aI","scrapeId":493937},{"matchId":"xKKV68Fa","scrapeId":493938},{"matchId":"rNIb4Fg1","scrapeId":493939},{"matchId":"GU3sbvXR","scrapeId":493940},{"matchId":"tIKOvt3j","scrapeId":493941},{"matchId":"ADhIXOeN","scrapeId":493942},{"matchId":"tvlEY4tH","scrapeId":493943},{"matchId":"pfqVYDz0","scrapeId":493944},{"matchId":"88I0JYzD","scrapeId":493945},{"matchId":"CtPiLf60","scrapeId":493946},{"matchId":"AwEh85rM","scrapeId":493947},{"matchId":"pEHhCdwt","scrapeId":493948},{"matchId":"8YwyfFNB","scrapeId":493949},{"matchId":"K85m3J0P","scrapeId":493950},{"matchId":"CrtAk0WP","scrapeId":493951},{"matchId":"fofvxs2Q","scrapeId":493952},{"matchId":"YayVRdvJ","scrapeId":493953},{"matchId":"Ik2TJstr","scrapeId":493954},{"matchId":"dx90G8Zk","scrapeId":493955},{"matchId":"ChpxpF39","scrapeId":493956},{"matchId":"bsRDPCC3","scrapeId":493957},{"matchId":"jy4n9iSM","scrapeId":493958},{"matchId":"2HO2F7Xb","scrapeId":493959},{"matchId":"SbWkI9mt","scrapeId":493960},{"matchId":"8f3T08I5","scrapeId":493961},{"matchId":"CAbp1HCl","scrapeId":493962},{"matchId":"2y9A7JZK","scrapeId":493963},{"matchId":"t6Wwf05L","scrapeId":493964},{"matchId":"tAnuZbTe","scrapeId":493965},{"matchId":"tn4hr369","scrapeId":493966},{"matchId":"p0OgN1Uq","scrapeId":493967},{"matchId":"dOnYEzfA","scrapeId":493968},{"matchId":"CKKulvt5","scrapeId":493969},{"matchId":"0pT32V1f","scrapeId":493970},{"matchId":"0WpuaXnf","scrapeId":493971},{"matchId":"C0i5Y7U8","scrapeId":493972},{"matchId":"rsushI9m","scrapeId":493973},{"matchId":"p2TPECbb","scrapeId":493974},{"matchId":"OnuHGYTo","scrapeId":493975},{"matchId":"bVxj2ZEh","scrapeId":493976},{"matchId":"d2GKnfF5","scrapeId":493977},{"matchId":"IigZzcGg","scrapeId":493978},{"matchId":"rNxaZquk","scrapeId":493979},{"matchId":"bk1Sv6HR","scrapeId":493980},{"matchId":"j3MqUl39","scrapeId":493981},{"matchId":"MTHuVUm3","scrapeId":493982},{"matchId":"GC28eUdp","scrapeId":493983},{"matchId":"dSLy1jZM","scrapeId":493984},{"matchId":"AiwVoKTI","scrapeId":493985},{"matchId":"UJnzcpxK","scrapeId":493986},{"matchId":"QRFwhzZf","scrapeId":493987},{"matchId":"CEjf0bRE","scrapeId":493988},{"matchId":"tzGPpJRR","scrapeId":493989},{"matchId":"CMptmlib","scrapeId":493990},{"matchId":"CMOAX8iB","scrapeId":493991},{"matchId":"QP2uITiO","scrapeId":493992},{"matchId":"hhIBOD8t","scrapeId":493993},{"matchId":"AFXs9Y8g","scrapeId":493994},{"matchId":"pClKgg96","scrapeId":493995},{"matchId":"W8pGfZg0","scrapeId":493996},{"matchId":"t2KctqZk","scrapeId":493997},{"matchId":"YkQNyJPt","scrapeId":493998},{"matchId":"rX7JCXoa","scrapeId":493999},{"matchId":"WhbI65J8","scrapeId":494000},{"matchId":"IXvSheLa","scrapeId":494001},{"matchId":"jocUI73m","scrapeId":494002},{"matchId":"IT4ORlZC","scrapeId":494003},{"matchId":"tlcf5zMr","scrapeId":494004},{"matchId":"voxE40vQ","scrapeId":494005},{"matchId":"QkYOOClh","scrapeId":494006},{"matchId":"CCesEE16","scrapeId":494007},{"matchId":"ht8V1hBk","scrapeId":494008},{"matchId":"8dhPobu6","scrapeId":494009},{"matchId":"nVNeKWN4","scrapeId":494010},{"matchId":"tvjBl7lF","scrapeId":494011},{"matchId":"b7EZnRnM","scrapeId":494012},{"matchId":"0pS4mkKc","scrapeId":494013},{"matchId":"WWEKKapf","scrapeId":494014},{"matchId":"vc0TmbEt","scrapeId":494015},{"matchId":"6cDiH2tJ","scrapeId":494016},{"matchId":"WjkZp4Ju","scrapeId":494017},{"matchId":"0WpBmeJ4","scrapeId":494018},{"matchId":"EafyyIZb","scrapeId":494019},{"matchId":"zToPyw3e","scrapeId":494020},{"matchId":"WUJQRH3q","scrapeId":494021},{"matchId":"O4fmEbZq","scrapeId":494022},{"matchId":"OlOouYx7","scrapeId":494023},{"matchId":"t6AaTzve","scrapeId":494024},{"matchId":"Szh7j7ui","scrapeId":494025},{"matchId":"IRDwguph","scrapeId":494026},{"matchId":"hjF7HDAa","scrapeId":494027},{"matchId":"fimxKEmF","scrapeId":494028},{"matchId":"OUJj8Hl3","scrapeId":494029},{"matchId":"QDEiHikO","scrapeId":494030},{"matchId":"I3T0D7Md","scrapeId":494031},{"matchId":"4SZAcG6j","scrapeId":494032},{"matchId":"IcdUpwNp","scrapeId":494033},{"matchId":"CfAviZXr","scrapeId":494034},{"matchId":"2LO8deAL","scrapeId":494035},{"matchId":"fHYkpRKb","scrapeId":494036},{"matchId":"b1mR4E30","scrapeId":494037},{"matchId":"pnF7Xmyg","scrapeId":494038},{"matchId":"CxDqCt9F","scrapeId":494039},{"matchId":"UHwthLHq","scrapeId":494040},{"matchId":"Cp9vsK6G","scrapeId":494041},{"matchId":"4vQOYKDc","scrapeId":494042},{"matchId":"MwyT6BOm","scrapeId":494043},{"matchId":"QFaZ0qdc","scrapeId":494044},{"matchId":"Wtn19MXN","scrapeId":494045},{"matchId":"lUY4o4dA","scrapeId":494046},{"matchId":"YcMXndGH","scrapeId":494047},{"matchId":"SSFK4PMk","scrapeId":494048},{"matchId":"WWAuMSB1","scrapeId":494049},{"matchId":"MiO6U6r5","scrapeId":494050},{"matchId":"ChBm3E5M","scrapeId":494051},{"matchId":"lExtpZbp","scrapeId":494052},{"matchId":"ltBFMat7","scrapeId":494053},{"matchId":"0v3AHDbA","scrapeId":494054},{"matchId":"by036SYB","scrapeId":494055},{"matchId":"zZ8rBjKt","scrapeId":494056},{"matchId":"zZnDeBKg","scrapeId":494057},{"matchId":"fH6c1tiF","scrapeId":494058},{"matchId":"K4BoGr1p","scrapeId":494059},{"matchId":"UwBiVHAJ","scrapeId":494060}]