[{"matchId":"hOMYHMlA","scrapeId":29651},{"matchId":"YD6a3NZG","scrapeId":29652},{"matchId":"dn20CP9N","scrapeId":29653},{"matchId":"xSMdq2ro","scrapeId":29654},{"matchId":"nNmvumia","scrapeId":29655},{"matchId":"CUI06irQ","scrapeId":29656},{"matchId":"x2Fmw2II","scrapeId":29657},{"matchId":"4YSHPrlJ","scrapeId":29658},{"matchId":"dAbRohON","scrapeId":29659},{"matchId":"WKhIyksE","scrapeId":29660},{"matchId":"IJaNnY8H","scrapeId":29661},{"matchId":"fHhZybyc","scrapeId":29662},{"matchId":"SdyiV3RA","scrapeId":29663},{"matchId":"ABZ4btat","scrapeId":29664},{"matchId":"SpPlG434","scrapeId":29665},{"matchId":"jHVJ4tMm","scrapeId":29666},{"matchId":"4E8Z7mYa","scrapeId":29667},{"matchId":"6aENuVl7","scrapeId":29668},{"matchId":"IegPzq7A","scrapeId":29669},{"matchId":"OKhH7pwO","scrapeId":29670},{"matchId":"UyIxdmvC","scrapeId":29671},{"matchId":"hvF4ARy8","scrapeId":29672},{"matchId":"W42EaANk","scrapeId":29673},{"matchId":"WtKR8E03","scrapeId":29674},{"matchId":"zaM4gZ0G","scrapeId":29675},{"matchId":"W63Isx24","scrapeId":29676},{"matchId":"ncEalmJJ","scrapeId":29677},{"matchId":"8jRXZm4Q","scrapeId":29678},{"matchId":"CMz1Cg62","scrapeId":29679},{"matchId":"M1RigWuK","scrapeId":29680},{"matchId":"WSxY8KaA","scrapeId":29681},{"matchId":"lQtweXJU","scrapeId":29682},{"matchId":"U1iv7wDP","scrapeId":29683},{"matchId":"QNcgdWj3","scrapeId":29684},{"matchId":"lnjAWdyD","scrapeId":29685},{"matchId":"pfggzuxl","scrapeId":29686},{"matchId":"bBzVqeIg","scrapeId":29687},{"matchId":"pMgeJn1d","scrapeId":29688},{"matchId":"veyA7k2p","scrapeId":29689},{"matchId":"4jlSZjRt","scrapeId":29690},{"matchId":"h8S25ha9","scrapeId":29691},{"matchId":"WAi7TmOO","scrapeId":29692},{"matchId":"KdF4bCPT","scrapeId":29693},{"matchId":"b19v6xRu","scrapeId":29694},{"matchId":"vaHX9oSD","scrapeId":29695},{"matchId":"O8SGr9TE","scrapeId":29696},{"matchId":"xIakQudj","scrapeId":29697},{"matchId":"SKihlhrt","scrapeId":29698},{"matchId":"tUd4GVSO","scrapeId":29699},{"matchId":"MqWUFbxE","scrapeId":29700},{"matchId":"4pgah4vj","scrapeId":29701},{"matchId":"lbCgomXM","scrapeId":29702},{"matchId":"xz3nvEJu","scrapeId":29703},{"matchId":"bZCrK057","scrapeId":29704},{"matchId":"AgGNPFSu","scrapeId":29705},{"matchId":"SYWx6TQB","scrapeId":29706},{"matchId":"C0ghcHtf","scrapeId":29707},{"matchId":"hxKFqbCf","scrapeId":29708},{"matchId":"runqgBqi","scrapeId":29709},{"matchId":"r5VZRYph","scrapeId":29710},{"matchId":"Mi47XC7O","scrapeId":29711},{"matchId":"8neur6PE","scrapeId":29712},{"matchId":"bHycVSu9","scrapeId":29713},{"matchId":"Q3HJH9B9","scrapeId":29714},{"matchId":"rLyLd8Zq","scrapeId":29715},{"matchId":"EVjBjXCA","scrapeId":29716},{"matchId":"AZ1NiMim","scrapeId":29717},{"matchId":"jBSpv3Nm","scrapeId":29718},{"matchId":"O0MzW5VQ","scrapeId":29719},{"matchId":"b1FqB4g1","scrapeId":29720},{"matchId":"Q7VyNkVb","scrapeId":29721},{"matchId":"8d4XfXo6","scrapeId":29722},{"matchId":"UFWrwTWh","scrapeId":29723},{"matchId":"Iuy14pJ2","scrapeId":29724},{"matchId":"nBwU9zgn","scrapeId":29725},{"matchId":"IReSko49","scrapeId":29726},{"matchId":"67Ahw8K3","scrapeId":29727},{"matchId":"vLnVL6kT","scrapeId":29728},{"matchId":"pKITDiih","scrapeId":29729},{"matchId":"WYeSZEHs","scrapeId":29730},{"matchId":"CUhkLEsL","scrapeId":29731},{"matchId":"h0QKdva3","scrapeId":29732},{"matchId":"bHZXj7Nc","scrapeId":29733},{"matchId":"W8QWWC10","scrapeId":29734},{"matchId":"nHY5WutE","scrapeId":29735},{"matchId":"pYRQwLWs","scrapeId":29736},{"matchId":"EB2u1CZT","scrapeId":29737},{"matchId":"zVQyKBNI","scrapeId":29738},{"matchId":"hprh3StA","scrapeId":29739},{"matchId":"SrnlZmST","scrapeId":29740},{"matchId":"AoKZXqo8","scrapeId":29741},{"matchId":"EaxuxyQK","scrapeId":29742},{"matchId":"j3UgOmnR","scrapeId":29743},{"matchId":"x0QkPTWK","scrapeId":29744},{"matchId":"rwRoQ9HE","scrapeId":29745},{"matchId":"4nSsRk28","scrapeId":29746},{"matchId":"WWlSvU5i","scrapeId":29747},{"matchId":"2XS8JTFk","scrapeId":29748},{"matchId":"rNCZ4U0d","scrapeId":29749},{"matchId":"dhVlgX1p","scrapeId":29750},{"matchId":"xSW04cAo","scrapeId":29751},{"matchId":"4zfg86BJ","scrapeId":29752},{"matchId":"UuKGfmsK","scrapeId":29753},{"matchId":"tK1Urjr8","scrapeId":29754},{"matchId":"AwQJVcho","scrapeId":29755},{"matchId":"reKJiwkn","scrapeId":29756},{"matchId":"424dc4nJ","scrapeId":29757},{"matchId":"p0SE6wUA","scrapeId":29758},{"matchId":"2B9DcDt2","scrapeId":29759},{"matchId":"xzP68aab","scrapeId":29760},{"matchId":"rmKE9JZd","scrapeId":29761},{"matchId":"GhIOBxjR","scrapeId":29762},{"matchId":"4tXneKK3","scrapeId":29763},{"matchId":"O8zqRu6N","scrapeId":29764},{"matchId":"8Yw8PSUI","scrapeId":29765},{"matchId":"SIrmUjGm","scrapeId":29766},{"matchId":"MsZlHqL1","scrapeId":29767},{"matchId":"lfdlZNuf","scrapeId":29768},{"matchId":"dIjUseSd","scrapeId":29769},{"matchId":"juU2RZsG","scrapeId":29770},{"matchId":"CWZzLC3n","scrapeId":29771},{"matchId":"v5df8ZJt","scrapeId":29772},{"matchId":"xABkfWpf","scrapeId":29773},{"matchId":"8fskFXMJ","scrapeId":29774},{"matchId":"OUwlisqk","scrapeId":29775},{"matchId":"0Igznn79","scrapeId":29776},{"matchId":"IZypyVhi","scrapeId":29777},{"matchId":"6Xk4zb2t","scrapeId":29778},{"matchId":"McogEixQ","scrapeId":29779},{"matchId":"WK8rJdX5","scrapeId":29780},{"matchId":"vPhneCVm","scrapeId":29781},{"matchId":"6ccZiKY6","scrapeId":29782},{"matchId":"lM2Uh0J0","scrapeId":29783},{"matchId":"6gR9GrfA","scrapeId":29784},{"matchId":"jkZY9wx2","scrapeId":29785},{"matchId":"CvCmbtwj","scrapeId":29786},{"matchId":"IsdzYqPp","scrapeId":29787},{"matchId":"0CSGdwOG","scrapeId":29788},{"matchId":"WANb03yb","scrapeId":29789},{"matchId":"xlQQKbsS","scrapeId":29790},{"matchId":"CK1G700a","scrapeId":29791},{"matchId":"2aVXnIPn","scrapeId":29792},{"matchId":"YcOujQ9I","scrapeId":29793},{"matchId":"Uo3ssVQm","scrapeId":29794},{"matchId":"CAWGQ9t7","scrapeId":29795},{"matchId":"MoNf2Zck","scrapeId":29796},{"matchId":"SrrWQcJh","scrapeId":29797},{"matchId":"feDH7zJU","scrapeId":29798},{"matchId":"GKCYNvh0","scrapeId":29799},{"matchId":"bqvyFPb5","scrapeId":29800},{"matchId":"vP6qn2jf","scrapeId":29801},{"matchId":"zZrhOiNJ","scrapeId":29802},{"matchId":"Yw0VCTYm","scrapeId":29803},{"matchId":"bokgufwA","scrapeId":29804},{"matchId":"fa3TOYhT","scrapeId":29805},{"matchId":"MoqjBFOT","scrapeId":29806},{"matchId":"EccoGn4s","scrapeId":29807},{"matchId":"4pFnhtND","scrapeId":29808},{"matchId":"tzne1Jw8","scrapeId":29809},{"matchId":"p6eOwPup","scrapeId":29810},{"matchId":"CY0amxDt","scrapeId":29811},{"matchId":"hARMZIrs","scrapeId":29812},{"matchId":"8QHT4bq7","scrapeId":29813},{"matchId":"00EL6KEf","scrapeId":29814},{"matchId":"tbMEATFS","scrapeId":29815},{"matchId":"KdgolC4r","scrapeId":29816},{"matchId":"AVqongXA","scrapeId":29817},{"matchId":"K6AdgkNt","scrapeId":29818},{"matchId":"fL6YlzWf","scrapeId":29819},{"matchId":"8jTixcnk","scrapeId":29820},{"matchId":"ttg1bs4p","scrapeId":29821},{"matchId":"xU32kGmU","scrapeId":29822},{"matchId":"fmBq1AFc","scrapeId":29823},{"matchId":"QozRdeJB","scrapeId":29824},{"matchId":"E3tim5uO","scrapeId":29825},{"matchId":"AkEZlms1","scrapeId":29826},{"matchId":"APt8HbVT","scrapeId":29827},{"matchId":"GOSdB52t","scrapeId":29828},{"matchId":"xIuVd6mm","scrapeId":29829},{"matchId":"AkpG2yK8","scrapeId":29830},{"matchId":"juUtlx5F","scrapeId":29831},{"matchId":"hQctp8np","scrapeId":29832},{"matchId":"Ozi1OiQN","scrapeId":29833},{"matchId":"nR35R2zl","scrapeId":29834},{"matchId":"nimd0Qyk","scrapeId":29835},{"matchId":"nFTvfkFF","scrapeId":29836},{"matchId":"Q1W7idgH","scrapeId":29837},{"matchId":"CIlHr1An","scrapeId":29838},{"matchId":"Y9Y7z4IP","scrapeId":29839},{"matchId":"O4bkUSsT","scrapeId":29840},{"matchId":"bTRWxxNQ","scrapeId":29841},{"matchId":"tIGfOrG3","scrapeId":29842},{"matchId":"GCWDQ7X3","scrapeId":29843},{"matchId":"fwKNFjJo","scrapeId":29844},{"matchId":"lrEfb2U7","scrapeId":29845},{"matchId":"C0kp2Xln","scrapeId":29846},{"matchId":"0MLRqjZH","scrapeId":29847},{"matchId":"hxM2g36E","scrapeId":29848},{"matchId":"UutZwO6R","scrapeId":29849},{"matchId":"ncOrT6h9","scrapeId":29850},{"matchId":"MguLDRhM","scrapeId":29851},{"matchId":"2DtSWTym","scrapeId":29852},{"matchId":"KQhJVr88","scrapeId":29853},{"matchId":"vB766XNs","scrapeId":29854},{"matchId":"pYRd0d18","scrapeId":29855},{"matchId":"foUPc3uA","scrapeId":29856},{"matchId":"nuNeykSu","scrapeId":29857},{"matchId":"vFcINVct","scrapeId":29858},{"matchId":"CnIP3y77","scrapeId":29859},{"matchId":"xEki7kd2","scrapeId":29860},{"matchId":"GzJeIF43","scrapeId":29861},{"matchId":"0dbvhkGH","scrapeId":29862},{"matchId":"f9KIkIUf","scrapeId":29863},{"matchId":"nNBlpGWl","scrapeId":29864},{"matchId":"QDAhqzne","scrapeId":29865},{"matchId":"YwE0sEG7","scrapeId":29866},{"matchId":"8pxr6CDt","scrapeId":29867},{"matchId":"pbRhmb71","scrapeId":29868},{"matchId":"Ayc9eMaL","scrapeId":29869},{"matchId":"xAccT3GS","scrapeId":29870},{"matchId":"dM2vHZQ5","scrapeId":29871},{"matchId":"SIdaKmG0","scrapeId":29872},{"matchId":"WjsL6Uo1","scrapeId":29873},{"matchId":"OjN3sEIk","scrapeId":29874},{"matchId":"AL8F34Zi","scrapeId":29875},{"matchId":"xEBFYqzI","scrapeId":29876},{"matchId":"jsLuM6jC","scrapeId":29877},{"matchId":"QgllWjEJ","scrapeId":29878},{"matchId":"zTXydJWk","scrapeId":29879},{"matchId":"O46RqWCc","scrapeId":29880},{"matchId":"bebme9BF","scrapeId":29881},{"matchId":"pEu8NUkp","scrapeId":29882},{"matchId":"61JooDQg","scrapeId":29883},{"matchId":"rNQfWHHo","scrapeId":29884},{"matchId":"OMPSUitD","scrapeId":29885},{"matchId":"C43YKGCl","scrapeId":29886},{"matchId":"WpbuvhgK","scrapeId":29887},{"matchId":"f1dlB6qN","scrapeId":29888},{"matchId":"UqfNd7UT","scrapeId":29889},{"matchId":"YHvqql0U","scrapeId":29890},{"matchId":"zky2JlJg","scrapeId":29891},{"matchId":"6sL1WAGO","scrapeId":29892},{"matchId":"QgnEZLQl","scrapeId":29893},{"matchId":"noYBxlQO","scrapeId":29894},{"matchId":"42vlV6Z2","scrapeId":29895},{"matchId":"MJnIBcHp","scrapeId":29896},{"matchId":"6oekiWZ0","scrapeId":29897},{"matchId":"EH17tFLr","scrapeId":29898},{"matchId":"6DJapOMG","scrapeId":29899},{"matchId":"0n1EYQN4","scrapeId":29900},{"matchId":"4K75zmgh","scrapeId":29901},{"matchId":"Wxt18U9a","scrapeId":29902},{"matchId":"KMbdDcLd","scrapeId":29903},{"matchId":"WQuLz1dj","scrapeId":29904},{"matchId":"QZ3EA0fk","scrapeId":29905},{"matchId":"6ud7TTsn","scrapeId":29906},{"matchId":"8AZ9Q64l","scrapeId":29907},{"matchId":"4dPd0Ajq","scrapeId":29908},{"matchId":"jVKvfZT9","scrapeId":29909},{"matchId":"dACCj0NH","scrapeId":29910},{"matchId":"4GmZxsgI","scrapeId":29911},{"matchId":"AJ7grHD0","scrapeId":29912},{"matchId":"YXdFUcq1","scrapeId":29913},{"matchId":"SjjnrSQo","scrapeId":29914},{"matchId":"bJMHPB14","scrapeId":29915},{"matchId":"xEyN3Uvo","scrapeId":29916},{"matchId":"jgkcaBaL","scrapeId":29917},{"matchId":"WUN1bZ25","scrapeId":29918},{"matchId":"U5Rp2H3t","scrapeId":29919},{"matchId":"p4SnoPSl","scrapeId":29920},{"matchId":"jJ2eQliM","scrapeId":29921},{"matchId":"SYvqiPha","scrapeId":29922},{"matchId":"4r8KZAET","scrapeId":29923},{"matchId":"KdDzzK8C","scrapeId":29924},{"matchId":"df0pP2ff","scrapeId":29925},{"matchId":"jTeF7gTH","scrapeId":29926},{"matchId":"OSM3CPAl","scrapeId":29927},{"matchId":"WCMknTdq","scrapeId":29928},{"matchId":"dKRWhvEb","scrapeId":29929},{"matchId":"nmq9waEB","scrapeId":29930},{"matchId":"nP0Mn3iP","scrapeId":29931},{"matchId":"OWjpEro0","scrapeId":29932},{"matchId":"8d8BSMrd","scrapeId":29933},{"matchId":"jsR5L5yT","scrapeId":29934},{"matchId":"8b9FAlNA","scrapeId":29935},{"matchId":"MsB7CAhb","scrapeId":29936},{"matchId":"hUJha0Is","scrapeId":29937},{"matchId":"0zeFoslr","scrapeId":29938},{"matchId":"6ev6wpdL","scrapeId":29939},{"matchId":"hhEWOpsS","scrapeId":29940},{"matchId":"I1MLAfMH","scrapeId":29941},{"matchId":"hWMXFUt0","scrapeId":29942},{"matchId":"8rLLIWds","scrapeId":29943},{"matchId":"djC4R6D2","scrapeId":29944},{"matchId":"KYSL2Nz2","scrapeId":29945},{"matchId":"MiY570t2","scrapeId":29946},{"matchId":"lKekf0On","scrapeId":29947},{"matchId":"YRas4zOi","scrapeId":29948},{"matchId":"rqKj8oxd","scrapeId":29949},{"matchId":"MBfRvV5p","scrapeId":29950},{"matchId":"EoVmRByo","scrapeId":29951},{"matchId":"GUXewIUu","scrapeId":29952},{"matchId":"WrHjUvhP","scrapeId":29953},{"matchId":"zcXxh6ws","scrapeId":29954},{"matchId":"8rLBT71E","scrapeId":29955},{"matchId":"OK2j5XId","scrapeId":29956},{"matchId":"IaDSq2Vj","scrapeId":29957},{"matchId":"phQug684","scrapeId":29958},{"matchId":"YZVsxEXC","scrapeId":29959},{"matchId":"hGbjnbeK","scrapeId":29960},{"matchId":"xQV4z1d8","scrapeId":29961},{"matchId":"xQ9ZKLdL","scrapeId":29962},{"matchId":"fNgkNjMi","scrapeId":29963},{"matchId":"4vjbjAiU","scrapeId":29964},{"matchId":"4C7fj0NG","scrapeId":29965},{"matchId":"08YWlF0J","scrapeId":29966},{"matchId":"pO8kzyho","scrapeId":29967},{"matchId":"vyZmkOf2","scrapeId":29968},{"matchId":"pnTpRDMQ","scrapeId":29969},{"matchId":"lnK5xoBd","scrapeId":29970},{"matchId":"4rCeRAc9","scrapeId":29971},{"matchId":"Gb5lDUso","scrapeId":29972},{"matchId":"AwU1ecef","scrapeId":29973},{"matchId":"4vWjRN6Q","scrapeId":29974},{"matchId":"IN79EpNK","scrapeId":29975},{"matchId":"vHKs0o8R","scrapeId":29976},{"matchId":"z5aqijPd","scrapeId":29977},{"matchId":"Mc38kwlh","scrapeId":29978},{"matchId":"0jFuhBhg","scrapeId":29979},{"matchId":"tAlAxWh6","scrapeId":29980},{"matchId":"tfAzn8TA","scrapeId":29981},{"matchId":"I7yKREvl","scrapeId":29982},{"matchId":"jut5XqB9","scrapeId":29983},{"matchId":"nobwJpdG","scrapeId":29984},{"matchId":"42tm8Tsb","scrapeId":29985},{"matchId":"hAcVknST","scrapeId":29986},{"matchId":"CCab1LUD","scrapeId":29987},{"matchId":"2NkMS0Ol","scrapeId":29988},{"matchId":"6XskUhrd","scrapeId":29989},{"matchId":"GS2l0ikm","scrapeId":29990},{"matchId":"U72zgzrK","scrapeId":29991},{"matchId":"vobhtxsH","scrapeId":29992},{"matchId":"x67R09N7","scrapeId":29993},{"matchId":"GWfyjh9k","scrapeId":29994},{"matchId":"4bUSOFAj","scrapeId":29995},{"matchId":"rNhDUpsC","scrapeId":29996},{"matchId":"tKk6JaHD","scrapeId":29997},{"matchId":"6L7zTClA","scrapeId":29998},{"matchId":"2RNIOIHi","scrapeId":29999},{"matchId":"x6aA5Ijn","scrapeId":30000},{"matchId":"1_jFfr52LG","scrapeId":30001},{"matchId":"1_rkiz7Oj4","scrapeId":30002},{"matchId":"1_rga65Jak","scrapeId":30003},{"matchId":"1_WhlmosUp","scrapeId":30004},{"matchId":"1_v7PGQWhU","scrapeId":30005},{"matchId":"1_23DytgNt","scrapeId":30006},{"matchId":"1_WtM8ShOH","scrapeId":30007},{"matchId":"1_tKJAdZ8D","scrapeId":30008},{"matchId":"1_QyJZAuxS","scrapeId":30009},{"matchId":"1_CvSg0H9l","scrapeId":30010},{"matchId":"1_d4cV78Bc","scrapeId":30011},{"matchId":"1_jTZUvAsB","scrapeId":30012},{"matchId":"1_S8sDU3r9","scrapeId":30013},{"matchId":"1_AkjEDXrC","scrapeId":30014},{"matchId":"1_E9BmXS97","scrapeId":30015},{"matchId":"1_r5LUF28r","scrapeId":30016},{"matchId":"1_ANklXbZQ","scrapeId":30017},{"matchId":"1_n1YO2eDd","scrapeId":30018},{"matchId":"1_nD4Q60j2","scrapeId":30019},{"matchId":"1_Kpu2c0yH","scrapeId":30020},{"matchId":"1_0OY6wupo","scrapeId":30021},{"matchId":"1_r7O9WWW0","scrapeId":30022},{"matchId":"1_WYc15fY1","scrapeId":30023},{"matchId":"1_byG7xOom","scrapeId":30024},{"matchId":"1_x8j4T6Ki","scrapeId":30025},{"matchId":"1_tCkKRY7t","scrapeId":30026},{"matchId":"1_jcg4bnLH","scrapeId":30027},{"matchId":"1_f39Gz2Ga","scrapeId":30028},{"matchId":"1_trSN3Mu0","scrapeId":30029},{"matchId":"1_fR3tiqdf","scrapeId":30030},{"matchId":"1_WCtMyxAD","scrapeId":30031},{"matchId":"1_QZRWzX5d","scrapeId":30032},{"matchId":"1_hGAA7VMO","scrapeId":30033},{"matchId":"1_noYzJbpB","scrapeId":30034},{"matchId":"1_SlgzeW1E","scrapeId":30035},{"matchId":"1_4OZ7FPwJ","scrapeId":30036},{"matchId":"1_vsrI6Ufl","scrapeId":30037},{"matchId":"1_pUJWzBAr","scrapeId":30038},{"matchId":"1_WGd9wWQ1","scrapeId":30039},{"matchId":"1_I1WfUKfJ","scrapeId":30040},{"matchId":"1_Ew7v5d2n","scrapeId":30041},{"matchId":"1_ldDnYFXO","scrapeId":30042},{"matchId":"1_nk8OwK3m","scrapeId":30043},{"matchId":"1_A37Gnf5k","scrapeId":30044},{"matchId":"1_OnyZ8pMi","scrapeId":30045},{"matchId":"1_vHdvghXb","scrapeId":30047},{"matchId":"1_niwSLkxP","scrapeId":30048},{"matchId":"1_b7lWfE2n","scrapeId":30049},{"matchId":"1_tYbqBYN6","scrapeId":30050},{"matchId":"1_phQ1bev1","scrapeId":30051}]