[{"matchId":"WWrDW1Lf","scrapeId":19251},{"matchId":"rXgVpers","scrapeId":19252},{"matchId":"QVwaPpER","scrapeId":19253},{"matchId":"2JF6Ty9o","scrapeId":19254},{"matchId":"6izvJlE3","scrapeId":19255},{"matchId":"69chXTTi","scrapeId":19256},{"matchId":"UZd0yMVr","scrapeId":19257},{"matchId":"lvWbNw74","scrapeId":19258},{"matchId":"23ewQD8U","scrapeId":19259},{"matchId":"CWPUC1EE","scrapeId":19260},{"matchId":"rVpdf1u6","scrapeId":19261},{"matchId":"lOy9SdMu","scrapeId":19262},{"matchId":"CGPDPZl1","scrapeId":19263},{"matchId":"xphSDxjk","scrapeId":19264},{"matchId":"YkA0awyd","scrapeId":19265},{"matchId":"CMtJn0ij","scrapeId":19266},{"matchId":"OvNU8j8h","scrapeId":19267},{"matchId":"xObmdDOn","scrapeId":19268},{"matchId":"pYDXvCgC","scrapeId":19269},{"matchId":"GvsrUfuf","scrapeId":19270},{"matchId":"rRM4GyBf","scrapeId":19271},{"matchId":"byzbKpCS","scrapeId":19272},{"matchId":"dYWj9anU","scrapeId":19273},{"matchId":"YVJ0brYB","scrapeId":19274},{"matchId":"0Slus7AB","scrapeId":19275},{"matchId":"I3azrme5","scrapeId":19276},{"matchId":"8t0e0dyB","scrapeId":19277},{"matchId":"hYmMHE8E","scrapeId":19278},{"matchId":"C47UekCD","scrapeId":19279},{"matchId":"hv9t7FKE","scrapeId":19280},{"matchId":"naBMtJ69","scrapeId":19281},{"matchId":"YeomSJiG","scrapeId":19282},{"matchId":"KYMJQ6GB","scrapeId":19283},{"matchId":"YNokBRGO","scrapeId":19284},{"matchId":"WUZf1jm0","scrapeId":19285},{"matchId":"IR9LniY6","scrapeId":19286},{"matchId":"8CnSU91R","scrapeId":19287},{"matchId":"URWmj5N1","scrapeId":19288},{"matchId":"vuJfDyPc","scrapeId":19289},{"matchId":"KU2LbxA4","scrapeId":19290},{"matchId":"YaLzmuBh","scrapeId":19291},{"matchId":"0jFoHvRO","scrapeId":19292},{"matchId":"0KSRHk36","scrapeId":19293},{"matchId":"rkadUjeD","scrapeId":19294},{"matchId":"KzKQL2Cg","scrapeId":19295},{"matchId":"IkCfJ9je","scrapeId":19296},{"matchId":"IVq97Ciq","scrapeId":19297},{"matchId":"hSUBXn0a","scrapeId":19298},{"matchId":"6VlTGGUd","scrapeId":19299},{"matchId":"IeTatzgp","scrapeId":19300},{"matchId":"QJZgWb42","scrapeId":19301},{"matchId":"SjjRauSF","scrapeId":19302},{"matchId":"MPRxJF7s","scrapeId":19303},{"matchId":"4GBZdIAr","scrapeId":19304},{"matchId":"S28DRaug","scrapeId":19305},{"matchId":"bRCt8Er3","scrapeId":19306},{"matchId":"rJdJQTAd","scrapeId":19307},{"matchId":"nVTG75yg","scrapeId":19308},{"matchId":"vcUCmEMk","scrapeId":19309},{"matchId":"8MVuSH0n","scrapeId":19310},{"matchId":"Szhetb3m","scrapeId":19311},{"matchId":"AuVMGZvJ","scrapeId":19312},{"matchId":"pWQQJq6l","scrapeId":19313},{"matchId":"As8J64CF","scrapeId":19314},{"matchId":"8EuXVkvC","scrapeId":19315},{"matchId":"QPQ0yzfD","scrapeId":19316},{"matchId":"Y3Py7na6","scrapeId":19317},{"matchId":"QwMT88Ug","scrapeId":19318},{"matchId":"IiyoECwa","scrapeId":19319},{"matchId":"0Y3lDBy8","scrapeId":19320},{"matchId":"zDR31Exd","scrapeId":19321},{"matchId":"hQgCBb03","scrapeId":19322},{"matchId":"YqTtdJ0G","scrapeId":19323},{"matchId":"v1h2pM14","scrapeId":19324},{"matchId":"4WySr9Qa","scrapeId":19325},{"matchId":"xdIpWVtf","scrapeId":19326},{"matchId":"YNZ1vfZD","scrapeId":19327},{"matchId":"xM1y5gre","scrapeId":19328},{"matchId":"bBvjgdqq","scrapeId":19329},{"matchId":"MRtJj3Np","scrapeId":19330},{"matchId":"23iK29Gu","scrapeId":19331},{"matchId":"0KGb3Lkg","scrapeId":19332},{"matchId":"nB3CiOjs","scrapeId":19333},{"matchId":"82LtdoQ4","scrapeId":19334},{"matchId":"2716eXiF","scrapeId":19335},{"matchId":"MmtXtYxM","scrapeId":19336},{"matchId":"42zkpbe9","scrapeId":19337},{"matchId":"0I30TE8M","scrapeId":19338},{"matchId":"CrhpXd9c","scrapeId":19339},{"matchId":"IHKYEsQl","scrapeId":19340},{"matchId":"YT4p2xAN","scrapeId":19341},{"matchId":"hE9P60eh","scrapeId":19342},{"matchId":"2P8PRROu","scrapeId":19343},{"matchId":"bwDZmnkD","scrapeId":19344},{"matchId":"dEGIiUkl","scrapeId":19345},{"matchId":"Ykby8mgU","scrapeId":19346},{"matchId":"xtIdnZD8","scrapeId":19347},{"matchId":"25tAdyM9","scrapeId":19348},{"matchId":"6JSyd4Vb","scrapeId":19349},{"matchId":"tbjip7Wn","scrapeId":19350},{"matchId":"SfQHV7Hg","scrapeId":19351},{"matchId":"ny5rH820","scrapeId":19352},{"matchId":"ER86PWfK","scrapeId":19353},{"matchId":"CpDX2Isj","scrapeId":19354},{"matchId":"GfutD25c","scrapeId":19355},{"matchId":"zwBq9KI7","scrapeId":19356},{"matchId":"jmIf156o","scrapeId":19357},{"matchId":"j9cCEjVs","scrapeId":19358},{"matchId":"lU6nMsj3","scrapeId":19359},{"matchId":"WOjjvSv4","scrapeId":19360},{"matchId":"Qyo8oNgt","scrapeId":19361},{"matchId":"WdvZtCmj","scrapeId":19362},{"matchId":"6NCKT7Ft","scrapeId":19363},{"matchId":"8booN2DP","scrapeId":19364},{"matchId":"Mw1MEV9o","scrapeId":19365},{"matchId":"SIdbAGIa","scrapeId":19366},{"matchId":"dGws4udQ","scrapeId":19367},{"matchId":"tSwwntzr","scrapeId":19368},{"matchId":"tOkZhfWR","scrapeId":19369},{"matchId":"WCvehNuH","scrapeId":19370},{"matchId":"vJFHv4BH","scrapeId":19371},{"matchId":"v3RgPOBU","scrapeId":19372},{"matchId":"WIa4E7cC","scrapeId":19373},{"matchId":"IwtGZg2S","scrapeId":19374},{"matchId":"d07iH9Dg","scrapeId":19375},{"matchId":"rVSTO0F2","scrapeId":19376},{"matchId":"d4P69LFF","scrapeId":19377},{"matchId":"MoBOdrW9","scrapeId":19378},{"matchId":"fZZTz19j","scrapeId":19379},{"matchId":"fcC8V5XA","scrapeId":19380},{"matchId":"IiDYo60f","scrapeId":19381},{"matchId":"0Gt8VpGD","scrapeId":19382},{"matchId":"6gaMdAvR","scrapeId":19383},{"matchId":"ChJFCTWd","scrapeId":19384},{"matchId":"UsTZEkCj","scrapeId":19385},{"matchId":"4MIFNMbg","scrapeId":19386},{"matchId":"bLkg6LTI","scrapeId":19387},{"matchId":"z5X1CyZf","scrapeId":19388},{"matchId":"zqdRabkk","scrapeId":19389},{"matchId":"nPfjboEp","scrapeId":19390},{"matchId":"jg9K37jN","scrapeId":19391},{"matchId":"vHpEdYxt","scrapeId":19392},{"matchId":"6TFawBxI","scrapeId":19393},{"matchId":"no6ymO9E","scrapeId":19394},{"matchId":"EXobZ4uF","scrapeId":19395},{"matchId":"I5WJLoBF","scrapeId":19396},{"matchId":"KA0k66BS","scrapeId":19397},{"matchId":"6X5Bf9CG","scrapeId":19398},{"matchId":"WEDbcBSc","scrapeId":19399},{"matchId":"I9tFWO0f","scrapeId":19400},{"matchId":"SfWHDBes","scrapeId":19401},{"matchId":"2w8LqXt1","scrapeId":19402},{"matchId":"z11qTw9F","scrapeId":19403},{"matchId":"dA2uUJg9","scrapeId":19404},{"matchId":"EoDzVav3","scrapeId":19405},{"matchId":"GM9SVAfm","scrapeId":19406},{"matchId":"0zTMOgmK","scrapeId":19407},{"matchId":"4lqK4Yel","scrapeId":19408},{"matchId":"p4nm2uzj","scrapeId":19409},{"matchId":"A9CAlM5j","scrapeId":19410},{"matchId":"AP6k1vYb","scrapeId":19411},{"matchId":"tWZajNJt","scrapeId":19412},{"matchId":"6FxTmUcr","scrapeId":19413},{"matchId":"dtRNviLR","scrapeId":19414},{"matchId":"27FSKVTe","scrapeId":19415},{"matchId":"d6AEDEMS","scrapeId":19416},{"matchId":"Q1x3eF0p","scrapeId":19417},{"matchId":"f1zcaO1I","scrapeId":19418},{"matchId":"zZSvnSlg","scrapeId":19419},{"matchId":"hG25jTIm","scrapeId":19420},{"matchId":"nFZrZRmD","scrapeId":19421},{"matchId":"ObHiurgk","scrapeId":19422},{"matchId":"nFJKxkXj","scrapeId":19423},{"matchId":"lbMSleQo","scrapeId":19424},{"matchId":"dAp2YZu5","scrapeId":19425},{"matchId":"Y7Bt8wSa","scrapeId":19426},{"matchId":"voY7ObCt","scrapeId":19427},{"matchId":"YeXF272i","scrapeId":19428},{"matchId":"K6GU0Vt5","scrapeId":19429},{"matchId":"YF5SfTiq","scrapeId":19430},{"matchId":"fL8MojFS","scrapeId":19431},{"matchId":"IPGBTjgp","scrapeId":19432},{"matchId":"EXD3ZLP5","scrapeId":19433},{"matchId":"SCZKspIP","scrapeId":19434},{"matchId":"6LDppIMQ","scrapeId":19435},{"matchId":"Agb6WbhR","scrapeId":19436},{"matchId":"pW8SK1gF","scrapeId":19437},{"matchId":"O4ddI8XG","scrapeId":19438},{"matchId":"badN6fck","scrapeId":19439},{"matchId":"jixJ4k3H","scrapeId":19440},{"matchId":"K0sgqhXm","scrapeId":19441},{"matchId":"6FhHN6Im","scrapeId":19442},{"matchId":"nRo9j62h","scrapeId":19443},{"matchId":"fThaVnC0","scrapeId":19444},{"matchId":"2cQBxqak","scrapeId":19445},{"matchId":"Srb9Uo7S","scrapeId":19446},{"matchId":"n5x4RcZj","scrapeId":19447},{"matchId":"bRCeJ0sU","scrapeId":19448},{"matchId":"p0QfNixl","scrapeId":19449},{"matchId":"rH9OUZqE","scrapeId":19450},{"matchId":"d0osId08","scrapeId":19451},{"matchId":"tUOB2H0L","scrapeId":19452},{"matchId":"2PpZlbWL","scrapeId":19453},{"matchId":"6wX0lRuB","scrapeId":19454},{"matchId":"Eq8Nz8BB","scrapeId":19455},{"matchId":"YPnlM8dI","scrapeId":19456},{"matchId":"4WJ2ABc6","scrapeId":19457},{"matchId":"48yGJFzK","scrapeId":19458},{"matchId":"UHJxydlc","scrapeId":19459},{"matchId":"YRyY6HZG","scrapeId":19460},{"matchId":"6FpHAazh","scrapeId":19461},{"matchId":"27qnct6h","scrapeId":19462},{"matchId":"Mk3W2BxE","scrapeId":19463},{"matchId":"nDOTrjor","scrapeId":19464},{"matchId":"nFPXQHPd","scrapeId":19465},{"matchId":"naqeUjWl","scrapeId":19466},{"matchId":"nw8KHDnq","scrapeId":19467},{"matchId":"Kl94jylp","scrapeId":19468},{"matchId":"2o0BD7kt","scrapeId":19469},{"matchId":"AiZ2SkkQ","scrapeId":19470},{"matchId":"l4FRgVr1","scrapeId":19471},{"matchId":"EoNEdXbr","scrapeId":19472},{"matchId":"nDri4O0i","scrapeId":19473},{"matchId":"vXjLj5Wi","scrapeId":19474},{"matchId":"MeKfzpnB","scrapeId":19475},{"matchId":"6JACN625","scrapeId":19476},{"matchId":"65Vw97mC","scrapeId":19477},{"matchId":"KU829Gse","scrapeId":19478},{"matchId":"WQHYGz36","scrapeId":19479},{"matchId":"hAoLtwjg","scrapeId":19480},{"matchId":"tCVkBF4m","scrapeId":19481},{"matchId":"jiAKkY7M","scrapeId":19482},{"matchId":"buQXFaC1","scrapeId":19483},{"matchId":"xn5EBpLF","scrapeId":19484},{"matchId":"Iob2Enyc","scrapeId":19485},{"matchId":"vXA2qSyN","scrapeId":19486},{"matchId":"jD9RsF0I","scrapeId":19487},{"matchId":"GKnAmJWt","scrapeId":19488},{"matchId":"dGgEHInD","scrapeId":19489},{"matchId":"MZMISreE","scrapeId":19490},{"matchId":"pz3ZWxV2","scrapeId":19491},{"matchId":"trxJSNwH","scrapeId":19492},{"matchId":"pdGOInAh","scrapeId":19493},{"matchId":"r9is69Qn","scrapeId":19494},{"matchId":"zqS3hjdm","scrapeId":19495},{"matchId":"zNjTuDCs","scrapeId":19496},{"matchId":"G0dAnOTd","scrapeId":19497},{"matchId":"zNxvkoe7","scrapeId":19498},{"matchId":"CblZPQz0","scrapeId":19499},{"matchId":"SvfpB17j","scrapeId":19500},{"matchId":"fVRgLQD0","scrapeId":19501},{"matchId":"ChcG77q1","scrapeId":19502},{"matchId":"feBpflF1","scrapeId":19503},{"matchId":"2cW51WMR","scrapeId":19504},{"matchId":"nm18hyvc","scrapeId":19505},{"matchId":"bTaXjO2h","scrapeId":19506},{"matchId":"b7OdvoJn","scrapeId":19507},{"matchId":"dv2RO5Ja","scrapeId":19508},{"matchId":"IBq6JAsK","scrapeId":19509},{"matchId":"UirVHc6F","scrapeId":19510},{"matchId":"2u3WddUk","scrapeId":19511},{"matchId":"4Uhi6073","scrapeId":19512},{"matchId":"SSa1vS6T","scrapeId":19513},{"matchId":"j3EgiXtU","scrapeId":19514},{"matchId":"00t8uzrI","scrapeId":19515},{"matchId":"fXOXuAvJ","scrapeId":19516},{"matchId":"nXURtPMf","scrapeId":19517},{"matchId":"UcR2utUc","scrapeId":19518},{"matchId":"v5lw3osU","scrapeId":19519},{"matchId":"WjymIzR7","scrapeId":19520},{"matchId":"On96BM8m","scrapeId":19521},{"matchId":"AND008gE","scrapeId":19522},{"matchId":"QHWd62UE","scrapeId":19523},{"matchId":"zHmENsOD","scrapeId":19524},{"matchId":"pSKLHize","scrapeId":19525},{"matchId":"OxQbLnRB","scrapeId":19526},{"matchId":"25QFLeLf","scrapeId":19527},{"matchId":"xlOl7d61","scrapeId":19528},{"matchId":"88A2ea7k","scrapeId":19529},{"matchId":"EokTt0hd","scrapeId":19530},{"matchId":"hILoUM8j","scrapeId":19531},{"matchId":"zNEZzYP5","scrapeId":19532},{"matchId":"l2ziqdIP","scrapeId":19533},{"matchId":"EcPBj1Br","scrapeId":19534},{"matchId":"SAEGoUMQ","scrapeId":19535},{"matchId":"WraxYAhR","scrapeId":19536},{"matchId":"CMhsEk1e","scrapeId":19537},{"matchId":"pfcSJKXG","scrapeId":19538},{"matchId":"Ctwk613H","scrapeId":19539},{"matchId":"2yk2dQZh","scrapeId":19540},{"matchId":"GMHduYb1","scrapeId":19541},{"matchId":"GEeEVtjC","scrapeId":19542},{"matchId":"n373TviU","scrapeId":19543},{"matchId":"fqk5kIM8","scrapeId":19544},{"matchId":"GvBSyah9","scrapeId":19545},{"matchId":"8hWqRsvi","scrapeId":19546},{"matchId":"6PNGRgD4","scrapeId":19547},{"matchId":"GIJTSrhs","scrapeId":19548},{"matchId":"GIcbD3hf","scrapeId":19549},{"matchId":"pEVi6noR","scrapeId":19550},{"matchId":"4pXknRge","scrapeId":19551},{"matchId":"EeI7ZmAk","scrapeId":19552},{"matchId":"EgHSC2A5","scrapeId":19553},{"matchId":"0lMWXzZp","scrapeId":19554},{"matchId":"xxxJSuc5","scrapeId":19555},{"matchId":"8dp2WNct","scrapeId":19556},{"matchId":"fkrdNpLP","scrapeId":19557},{"matchId":"ELqf3PTg","scrapeId":19558},{"matchId":"YDWUvc6N","scrapeId":19559},{"matchId":"z7bhO5lM","scrapeId":19560},{"matchId":"Mmx0stOH","scrapeId":19561},{"matchId":"n9btdm5T","scrapeId":19562},{"matchId":"zVpOVnc1","scrapeId":19563},{"matchId":"MX9KWT8E","scrapeId":19564},{"matchId":"0MgQqZFH","scrapeId":19565},{"matchId":"CnKWnx0U","scrapeId":19566},{"matchId":"jH3c6HGa","scrapeId":19567},{"matchId":"61wzpjn4","scrapeId":19568},{"matchId":"bwqmcrLs","scrapeId":19569},{"matchId":"CIrZkRDE","scrapeId":19570},{"matchId":"tzx3mYiG","scrapeId":19571},{"matchId":"GIZyZYxN","scrapeId":19572},{"matchId":"nw0K7dvO","scrapeId":19573},{"matchId":"tIEPIMnP","scrapeId":19574},{"matchId":"8WIaCa8e","scrapeId":19575},{"matchId":"COwPI1VR","scrapeId":19576},{"matchId":"fkx8BPM8","scrapeId":19577},{"matchId":"0jeHl2Fe","scrapeId":19578},{"matchId":"vFJ1fXoH","scrapeId":19579},{"matchId":"O8xQbRL5","scrapeId":19580},{"matchId":"445ar6yP","scrapeId":19581},{"matchId":"UoiHVSiJ","scrapeId":19582},{"matchId":"tpsZVyn2","scrapeId":19583},{"matchId":"AVgejzxE","scrapeId":19584},{"matchId":"nDGWlsBE","scrapeId":19585},{"matchId":"xCbjv0vM","scrapeId":19586},{"matchId":"zDNH6LIj","scrapeId":19587},{"matchId":"GStoCseT","scrapeId":19588},{"matchId":"lhN3a4BN","scrapeId":19589},{"matchId":"vJXJaD56","scrapeId":19590},{"matchId":"AF1mAaSn","scrapeId":19591},{"matchId":"WID2zcxe","scrapeId":19592},{"matchId":"h4zGq1F8","scrapeId":19593},{"matchId":"6ZlKr0DH","scrapeId":19594},{"matchId":"Gpd7o2Tb","scrapeId":19595},{"matchId":"WhhkuR6P","scrapeId":19596},{"matchId":"dbICR7xQ","scrapeId":19597},{"matchId":"44gZDl8Q","scrapeId":19598},{"matchId":"S6hZf91l","scrapeId":19599},{"matchId":"QVgjbt2p","scrapeId":19600},{"matchId":"0YDB203c","scrapeId":19601},{"matchId":"8vkYlsZc","scrapeId":19602},{"matchId":"6VIiElTq","scrapeId":19603},{"matchId":"I7JBQNc9","scrapeId":19604},{"matchId":"80hFl4Qu","scrapeId":19605},{"matchId":"YLlGml0b","scrapeId":19606},{"matchId":"ppYUmSR8","scrapeId":19607},{"matchId":"IP6slpa2","scrapeId":19608},{"matchId":"IFZXjFat","scrapeId":19609},{"matchId":"vPEbxGpm","scrapeId":19610},{"matchId":"hEwUMzo0","scrapeId":19611},{"matchId":"M5wpRUKl","scrapeId":19612},{"matchId":"4A8PNeEd","scrapeId":19613},{"matchId":"bep8HKiN","scrapeId":19614},{"matchId":"rJzQ4s8H","scrapeId":19615},{"matchId":"UFAjjrgO","scrapeId":19616},{"matchId":"Uutngp95","scrapeId":19617},{"matchId":"02JywYI7","scrapeId":19618},{"matchId":"zssiRzKe","scrapeId":19619},{"matchId":"MDPuLacM","scrapeId":19620},{"matchId":"Sftw1v6j","scrapeId":19621},{"matchId":"Iu3QM0BC","scrapeId":19622},{"matchId":"rNlrANR6","scrapeId":19623},{"matchId":"pStM0ovK","scrapeId":19624},{"matchId":"0zaXmmwH","scrapeId":19625},{"matchId":"lQphfvcn","scrapeId":19626},{"matchId":"2wj3ve0j","scrapeId":19627},{"matchId":"AgKRNne2","scrapeId":19628},{"matchId":"WlOZroT7","scrapeId":19629},{"matchId":"MiGx7cFc","scrapeId":19630},{"matchId":"nZ1ffKVi","scrapeId":19631},{"matchId":"4tkYvuW4","scrapeId":19632},{"matchId":"z1ynTsXh","scrapeId":19633},{"matchId":"xQeBZqfP","scrapeId":19634},{"matchId":"8YJ1JX3R","scrapeId":19635},{"matchId":"zyWgb7mO","scrapeId":19636},{"matchId":"2FHAbWR1","scrapeId":19637},{"matchId":"bJWk9SOM","scrapeId":19638},{"matchId":"EavKlttm","scrapeId":19639},{"matchId":"4I2l1DQo","scrapeId":19640},{"matchId":"I796twkJ","scrapeId":19641},{"matchId":"69NFjNCQ","scrapeId":19642},{"matchId":"WhCkzEjK","scrapeId":19643},{"matchId":"ImsLUuj7","scrapeId":19644},{"matchId":"ALhoCXtt","scrapeId":19645},{"matchId":"r7lfQQbL","scrapeId":19646},{"matchId":"vcjY4l6j","scrapeId":19647},{"matchId":"QNLuDUbU","scrapeId":19648},{"matchId":"j3fNFOYL","scrapeId":19649},{"matchId":"SQMqocvt","scrapeId":19650}]